riscv_ai_accelerator.srcs/sources_1/new/ai_accel_controller.v
`timescale 1ns/1ps

module ai_accel_controller (

    input  clk,
    input  rst,

    // Start computation
    input start,

    // Number of computation cycles
    input [7:0] compute_cycles,

    // Status
    output reg busy,
    output reg done,

    // Control for accelerator datapath
    output reg load_enable,
    output reg compute_enable,

    // Current state for debugging
    output reg [1:0] state

);


    // =========================================================
    // FSM STATES
    // =========================================================

    localparam STATE_IDLE    = 2'b00;
    localparam STATE_LOAD    = 2'b01;
    localparam STATE_COMPUTE = 2'b10;
    localparam STATE_DONE    = 2'b11;


    // =========================================================
    // Internal registers
    // =========================================================

    reg [7:0] cycle_count;


    // =========================================================
    // State machine
    // =========================================================

    always @(posedge clk or posedge rst) begin

        if (rst) begin

            state       <= STATE_IDLE;

            cycle_count <= 8'd0;

        end

        else begin

            case (state)

                // =================================================
                // IDLE
                // =================================================

                STATE_IDLE: begin

                    cycle_count <= 8'd0;

                    if (start)
                        state <= STATE_LOAD;

                end


                // =================================================
                // LOAD
                // =================================================

                STATE_LOAD: begin

                    cycle_count <= 8'd0;

                    state <= STATE_COMPUTE;

                end


                // =================================================
                // COMPUTE
                // =================================================

                STATE_COMPUTE: begin

                    if (cycle_count >= compute_cycles - 1'b1) begin

                        cycle_count <= 8'd0;

                        state <= STATE_DONE;

                    end

                    else begin

                        cycle_count <= cycle_count + 1'b1;

                    end

                end


                // =================================================
                // DONE
                // =================================================

                STATE_DONE: begin

                    state <= STATE_IDLE;

                end


                // =================================================
                // DEFAULT
                // =================================================

                default: begin

                    state <= STATE_IDLE;

                    cycle_count <= 8'd0;

                end

            endcase

        end

    end


    // =========================================================
    // Output logic
    // =========================================================

    always @(*) begin

        // -----------------------------------------------------
        // Defaults
        // -----------------------------------------------------

        busy = 1'b0;

        done = 1'b0;

        load_enable = 1'b0;

        compute_enable = 1'b0;


        case (state)

            // -------------------------------------------------
            // IDLE
            // -------------------------------------------------

            STATE_IDLE: begin

                busy = 1'b0;

            end


            // -------------------------------------------------
            // LOAD
            // -------------------------------------------------

            STATE_LOAD: begin

                busy = 1'b1;

                load_enable = 1'b1;

            end


            // -------------------------------------------------
            // COMPUTE
            // -------------------------------------------------

            STATE_COMPUTE: begin

                busy = 1'b1;

                compute_enable = 1'b1;

            end


            // -------------------------------------------------
            // DONE
            // -------------------------------------------------

            STATE_DONE: begin

                busy = 1'b0;

                done = 1'b1;

            end


            default: begin

                busy = 1'b0;

            end

        endcase

    end

endmodule

riscv_ai_accelerator.srcs/sim_1/new/tb_ai_accel_controller.v
`timescale 1ns/1ps

module tb_ai_accel_controller;

    reg clk;
    reg rst;

    reg start;

    reg [7:0] compute_cycles;

    wire busy;
    wire done;

    wire load_enable;
    wire compute_enable;

    wire [1:0] state;


    // =========================================================
    // DUT
    // =========================================================

    ai_accel_controller DUT (

        .clk(clk),
        .rst(rst),

        .start(start),

        .compute_cycles(compute_cycles),

        .busy(busy),
        .done(done),

        .load_enable(load_enable),
        .compute_enable(compute_enable),

        .state(state)

    );


    // =========================================================
    // CLOCK
    // =========================================================

    initial begin

        clk = 1'b0;

        forever #5 clk = ~clk;

    end


    // =========================================================
    // TEST
    // =========================================================

    initial begin

        rst = 1'b1;

        start = 1'b0;

        compute_cycles = 8'd4;


        // =====================================================
        // RESET
        // =====================================================

        #20;

        rst = 1'b0;

        #10;


        // =====================================================
        // TEST 1
        //
        // Controller should be IDLE
        // =====================================================

        $display("");
        $display("========================================");
        $display("TEST 1 - IDLE");
        $display("========================================");

        $display("BUSY = %b", busy);
        $display("DONE = %b", done);

        if ((busy == 1'b0) &&
            (done == 1'b0))
            $display("PASS");
        else
            $display("FAIL");


        // =====================================================
        // TEST 2
        //
        // START
        // =====================================================

        @(negedge clk);

        start = 1'b1;

        @(negedge clk);

        start = 1'b0;

        #1;

        $display("");
        $display("========================================");
        $display("TEST 2 - LOAD");
        $display("========================================");

        $display("BUSY        = %b", busy);
        $display("LOAD_ENABLE = %b", load_enable);
        $display("DONE        = %b", done);

        if ((busy == 1'b1) &&
            (load_enable == 1'b1) &&
            (done == 1'b0))
            $display("PASS");
        else
            $display("FAIL");


        // =====================================================
        // TEST 3
        //
        // COMPUTE
        // =====================================================

        @(negedge clk);

        #1;

        $display("");
        $display("========================================");
        $display("TEST 3 - COMPUTE");
        $display("========================================");

        $display("BUSY           = %b", busy);
        $display("COMPUTE_ENABLE = %b", compute_enable);

        if ((busy == 1'b1) &&
            (compute_enable == 1'b1))
            $display("PASS");
        else
            $display("FAIL");


        // =====================================================
        // TEST 4
        //
        // Wait for computation to finish
        // =====================================================

        repeat (4)
            @(negedge clk);

        #1;

        $display("");
        $display("========================================");
        $display("TEST 4 - DONE");
        $display("========================================");

        $display("BUSY = %b", busy);
        $display("DONE = %b", done);

        if ((busy == 1'b0) &&
            (done == 1'b1))
            $display("PASS");
        else
            $display("FAIL");


        // =====================================================
        // TEST 5
        //
        // DONE should return to IDLE
        // =====================================================

        @(negedge clk);

        #1;

        $display("");
        $display("========================================");
        $display("TEST 5 - RETURN TO IDLE");
        $display("========================================");

        $display("BUSY = %b", busy);
        $display("DONE = %b", done);

        if ((busy == 1'b0) &&
            (done == 1'b0))
            $display("PASS");
        else
            $display("FAIL");


        // =====================================================
        // COMPLETE
        // =====================================================

        $display("");
        $display("========================================");
        $display("AI ACCELERATOR CONTROLLER TEST COMPLETE");
        $display("========================================");

        #20;

        $finish;

    end


    // =========================================================
    // WAVEFORM
    // =========================================================

    initial begin

        $dumpfile("ai_accel_controller.vcd");

        $dumpvars(0, tb_ai_accel_controller);

    end

endmodule

riscv_ai_accelerator.sim/sim_1/behav/xsim/ai_accel_controller.vcd
$date
   Fri Aug 14 09:45:38 2026
$end

$version
  2026.1
  $dumpfile ("ai_accel_controller.vcd") 
$end

$timescale
  1ps
$end

$scope module tb_ai_accel_controller $end
$var reg 1 ! clk $end
$var reg 1 " rst $end
$var reg 1 # start $end
$var reg 8 $ compute_cycles [7:0] $end
$var wire 1 % busy $end
$var wire 1 & done $end
$var wire 1 ' load_enable $end
$var wire 1 ( compute_enable $end
$var wire 2 ) state [1:0] $end
$scope module DUT $end
$var wire 1 * clk $end
$var wire 1 + rst $end
$var wire 1 , start $end
$var wire 8 - compute_cycles [7:0] $end
$var reg 1 . busy $end
$var reg 1 / done $end
$var reg 1 0 load_enable $end
$var reg 1 1 compute_enable $end
$var reg 2 2 state [1:0] $end
$var reg 8 3 cycle_count [7:0] $end
$upscope $end
$upscope $end
$enddefinitions $end

#0
$dumpvars
0!
1"
0#
b100 $
0%
0&
0'
0(
b0 )
0*
1+
0,
b100 -
0.
0/
00
01
b0 2
b0 3
$end

#5000
1!
1*

#10000
0!
0*

#15000
1!
1*

#20000
0!
0"
0*
0+

#25000
1!
1*

#30000
0!
1#
0*
1,

#35000
1!
1%
1'
b1 )
1*
1.
10
b1 2

#40000
0!
0#
0*
0,

#45000
1!
0'
1(
b10 )
1*
1.
00
11
b10 2

#50000
0!
0*

#55000
1!
1*
b1 3

#60000
0!
0*

#65000
1!
1*
b10 3

#70000
0!
0*

#75000
1!
1*
b11 3

#80000
0!
0*

#85000
1!
0%
1&
0(
b11 )
1*
0.
1/
01
b11 2
b0 3

#90000
0!
0*

#95000
1!
0&
b0 )
1*
0/
b0 2

