riscv_ai_accelerator.srcs/sources_1/new/ai_matrix_buffer.v
`timescale 1ns/1ps

module ai_matrix_buffer (

    input clk,
    input rst,

    // =========================================================
    // Matrix A write interface
    // =========================================================

    input        a_write_enable,
    input  [1:0]  a_write_addr,
    input [31:0] a_write_data,


    // =========================================================
    // Matrix B write interface
    // =========================================================

    input        b_write_enable,
    input  [1:0]  b_write_addr,
    input [31:0] b_write_data,


    // =========================================================
    // Matrix A read interface
    // =========================================================

    input  [1:0]  a_read_addr,
    output reg [31:0] a_read_data,


    // =========================================================
    // Matrix B read interface
    // =========================================================

    input  [1:0]  b_read_addr,
    output reg [31:0] b_read_data

);


    // =========================================================
    // Matrix storage
    //
    // Four 32-bit words for A
    // Four 32-bit words for B
    // =========================================================

    reg [31:0] matrix_a [0:3];

    reg [31:0] matrix_b [0:3];

    integer i;


    // =========================================================
    // WRITE LOGIC
    // =========================================================

    always @(posedge clk or posedge rst) begin

        if (rst) begin

            for (i = 0; i < 4; i = i + 1) begin

                matrix_a[i] <= 32'd0;

                matrix_b[i] <= 32'd0;

            end

        end

        else begin

            if (a_write_enable)
                matrix_a[a_write_addr] <= a_write_data;

            if (b_write_enable)
                matrix_b[b_write_addr] <= b_write_data;

        end

    end


    // =========================================================
    // READ MATRIX A
    // =========================================================

    always @(*) begin

        a_read_data = matrix_a[a_read_addr];

    end


    // =========================================================
    // READ MATRIX B
    // =========================================================

    always @(*) begin

        b_read_data = matrix_b[b_read_addr];

    end


endmodule

riscv_ai_accelerator.srcs/sim_1/new/tb_ai_matrix_buffer.v
`timescale 1ns/1ps

module tb_ai_matrix_buffer;

    reg clk;
    reg rst;


    // =========================================================
    // Matrix A interface
    // =========================================================

    reg        a_write_enable;
    reg [1:0]  a_write_addr;
    reg [31:0] a_write_data;

    reg [1:0]  a_read_addr;
    wire [31:0] a_read_data;


    // =========================================================
    // Matrix B interface
    // =========================================================

    reg        b_write_enable;
    reg [1:0]  b_write_addr;
    reg [31:0] b_write_data;

    reg [1:0]  b_read_addr;
    wire [31:0] b_read_data;


    // =========================================================
    // DUT
    // =========================================================

    ai_matrix_buffer DUT (

        .clk(clk),
        .rst(rst),

        .a_write_enable(a_write_enable),
        .a_write_addr(a_write_addr),
        .a_write_data(a_write_data),

        .b_write_enable(b_write_enable),
        .b_write_addr(b_write_addr),
        .b_write_data(b_write_data),

        .a_read_addr(a_read_addr),
        .a_read_data(a_read_data),

        .b_read_addr(b_read_addr),
        .b_read_data(b_read_data)

    );


    // =========================================================
    // CLOCK
    // =========================================================

    initial begin

        clk = 1'b0;

        forever #5 clk = ~clk;

    end


    // =========================================================
    // TEST
    // =========================================================

    initial begin

        rst = 1'b1;

        a_write_enable = 1'b0;
        b_write_enable = 1'b0;

        a_write_addr = 2'd0;
        b_write_addr = 2'd0;

        a_write_data = 32'd0;
        b_write_data = 32'd0;

        a_read_addr = 2'd0;
        b_read_addr = 2'd0;


        // =====================================================
        // RESET
        // =====================================================

        #20;

        rst = 1'b0;


        // =====================================================
        // WRITE MATRIX A
        //
        // A =
        //
        //  1   2   3   4
        //  5   6   7   8
        //  9  10  11  12
        // 13  14  15  16
        // =====================================================

        @(negedge clk);

        a_write_enable = 1'b1;
        a_write_addr = 2'd0;

        a_write_data = {
            8'd4,
            8'd3,
            8'd2,
            8'd1
        };


        @(negedge clk);

        a_write_addr = 2'd1;

        a_write_data = {
            8'd8,
            8'd7,
            8'd6,
            8'd5
        };


        @(negedge clk);

        a_write_addr = 2'd2;

        a_write_data = {
            8'd12,
            8'd11,
            8'd10,
            8'd9
        };


        @(negedge clk);

        a_write_addr = 2'd3;

        a_write_data = {
            8'd16,
            8'd15,
            8'd14,
            8'd13
        };


        @(negedge clk);

        a_write_enable = 1'b0;


        // =====================================================
        // WRITE MATRIX B
        //
        // Identity matrix
        //
        // 1 0 0 0
        // 0 1 0 0
        // 0 0 1 0
        // 0 0 0 1
        // =====================================================

        b_write_enable = 1'b1;

        b_write_addr = 2'd0;

        b_write_data = {
            8'd0,
            8'd0,
            8'd0,
            8'd1
        };


        @(negedge clk);

        b_write_addr = 2'd1;

        b_write_data = {
            8'd0,
            8'd0,
            8'd1,
            8'd0
        };


        @(negedge clk);

        b_write_addr = 2'd2;

        b_write_data = {
            8'd0,
            8'd1,
            8'd0,
            8'd0
        };


        @(negedge clk);

        b_write_addr = 2'd3;

        b_write_data = {
            8'd1,
            8'd0,
            8'd0,
            8'd0
        };


        @(negedge clk);

        b_write_enable = 1'b0;


        // =====================================================
        // READ BACK MATRIX A
        // =====================================================

        a_read_addr = 2'd0;

        #2;

        $display("");
        $display("========================================");
        $display("MATRIX BUFFER TEST");
        $display("========================================");

        $display("");
        $display("A ROW 0 = %h", a_read_data);


        if (a_read_data ==
            {8'd4,8'd3,8'd2,8'd1})

            $display("A ROW 0 PASS");

        else

            $display("A ROW 0 FAIL");


        a_read_addr = 2'd1;

        #2;

        $display("A ROW 1 = %h", a_read_data);

        if (a_read_data ==
            {8'd8,8'd7,8'd6,8'd5})

            $display("A ROW 1 PASS");

        else

            $display("A ROW 1 FAIL");


        // =====================================================
        // READ MATRIX B
        // =====================================================

        b_read_addr = 2'd0;

        #2;

        $display("");
        $display("B ROW 0 = %h", b_read_data);

        if (b_read_data ==
            {8'd0,8'd0,8'd0,8'd1})

            $display("B ROW 0 PASS");

        else

            $display("B ROW 0 FAIL");


        b_read_addr = 2'd3;

        #2;

        $display("B ROW 3 = %h", b_read_data);

        if (b_read_data ==
            {8'd1,8'd0,8'd0,8'd0})

            $display("B ROW 3 PASS");

        else

            $display("B ROW 3 FAIL");


        // =====================================================
        // COMPLETE
        // =====================================================

        $display("");
        $display("========================================");
        $display("MATRIX BUFFER TEST COMPLETE");
        $display("========================================");

        #20;

        $finish;

    end


    // =========================================================
    // WAVEFORM
    // =========================================================

    initial begin

        $dumpfile("ai_matrix_buffer.vcd");

        $dumpvars(0, tb_ai_matrix_buffer);

    end

endmodule

riscv_ai_accelerator.sim/sim_1/behav/xsim/ai_matrix_buffer.vcd
$date
   Fri Aug 14 09:54:58 2026
$end

$version
  2026.1
  $dumpfile ("ai_matrix_buffer.vcd") 
$end

$timescale
  1ps
$end

$scope module tb_ai_matrix_buffer $end
$var reg 1 ! clk $end
$var reg 1 " rst $end
$var reg 1 # a_write_enable $end
$var reg 2 $ a_write_addr [1:0] $end
$var reg 32 % a_write_data [31:0] $end
$var reg 2 & a_read_addr [1:0] $end
$var wire 32 ' a_read_data [31:0] $end
$var reg 1 ( b_write_enable $end
$var reg 2 ) b_write_addr [1:0] $end
$var reg 32 * b_write_data [31:0] $end
$var reg 2 + b_read_addr [1:0] $end
$var wire 32 , b_read_data [31:0] $end
$scope module DUT $end
$var wire 1 - clk $end
$var wire 1 . rst $end
$var wire 1 / a_write_enable $end
$var wire 2 0 a_write_addr [1:0] $end
$var wire 32 1 a_write_data [31:0] $end
$var wire 1 2 b_write_enable $end
$var wire 2 3 b_write_addr [1:0] $end
$var wire 32 4 b_write_data [31:0] $end
$var wire 2 5 a_read_addr [1:0] $end
$var reg 32 6 a_read_data [31:0] $end
$var wire 2 7 b_read_addr [1:0] $end
$var reg 32 8 b_read_data [31:0] $end
$var integer 32 9 i [31:0] $end
$upscope $end
$upscope $end
$enddefinitions $end

#0
$dumpvars
0!
1"
0#
b0 $
b0 %
b0 &
b0 '
0(
b0 )
b0 *
b0 +
b0 ,
0-
1.
0/
b0 0
b0 1
02
b0 3
b0 4
b0 5
b0 6
b0 7
b0 8
bx 9
$end

#5000
1!
1-

#10000
0!
0-

#15000
1!
1-

#20000
0!
0"
1#
b100000000110000001000000001 %
0-
0.
1/
b100000000110000001000000001 1

#25000
1!
b100000000110000001000000001 '
1-
b100000000110000001000000001 6

#30000
0!
b1 $
b1000000001110000011000000101 %
0-
b1 0
b1000000001110000011000000101 1

#35000
1!
1-

#40000
0!
b10 $
b1100000010110000101000001001 %
0-
b10 0
b1100000010110000101000001001 1

#45000
1!
1-

#50000
0!
b11 $
b10000000011110000111000001101 %
0-
b11 0
b10000000011110000111000001101 1

#55000
1!
1-

#60000
0!
0#
1(
b1 *
0-
0/
12
b1 4

#65000
1!
b1 ,
1-
b1 8

#70000
0!
b1 )
b100000000 *
0-
b1 3
b100000000 4

#75000
1!
1-

#80000
0!
b10 )
b10000000000000000 *
0-
b10 3
b10000000000000000 4

#85000
1!
1-

#90000
0!
b11 )
b1000000000000000000000000 *
0-
b11 3
b1000000000000000000000000 4

#95000
1!
1-

#100000
0!
0(
0-
02

#102000
b1 &
b1000000001110000011000000101 '
b1 5
b1000000001110000011000000101 6

#105000
1!
1-

#106000
b11 +
b1000000000000000000000000 ,
b11 7
b1000000000000000000000000 8

