riscv_ai_accelerator.srcs/sources_1/new/ai_pe.v
`timescale 1ns/1ps

module ai_pe (

    input               clk,
    input               rst,

    input               enable,

    input signed [7:0]  a_in,
    input signed [7:0]  b_in,

    output reg signed [7:0]  a_out,
    output reg signed [7:0]  b_out,

    output reg signed [31:0] accumulator

);

    reg signed [15:0] product;


    always @(posedge clk or posedge rst) begin

        if (rst) begin

            a_out      <= 8'sd0;
            b_out      <= 8'sd0;

            accumulator <= 32'sd0;

        end

        else if (enable) begin

            // -------------------------------------------------
            // Pass operands to neighboring PE
            // -------------------------------------------------

            a_out <= a_in;

            b_out <= b_in;


            // -------------------------------------------------
            // INT8 multiplication
            // -------------------------------------------------

            product = a_in * b_in;


            // -------------------------------------------------
            // Accumulate
            // -------------------------------------------------

            accumulator <= accumulator + product;

        end

    end

endmodule

riscv_ai_accelerator.srcs/sim_1/new/tb_ai_pe.v
`timescale 1ns/1ps

module tb_ai_pe;

    reg clk;
    reg rst;

    reg enable;

    reg signed [7:0] a_in;
    reg signed [7:0] b_in;

    wire signed [7:0] a_out;
    wire signed [7:0] b_out;

    wire signed [31:0] accumulator;


    // =========================================================
    // DUT
    // =========================================================

    ai_pe DUT (

        .clk(clk),
        .rst(rst),

        .enable(enable),

        .a_in(a_in),
        .b_in(b_in),

        .a_out(a_out),
        .b_out(b_out),

        .accumulator(accumulator)

    );


    // =========================================================
    // Clock
    // =========================================================

    initial begin

        clk = 1'b0;

        forever #5 clk = ~clk;

    end


    // =========================================================
    // Test
    // =========================================================

    initial begin

        rst = 1'b1;

        enable = 1'b0;

        a_in = 8'sd0;
        b_in = 8'sd0;

        #20;

        rst = 1'b0;


        // =====================================================
        // TEST 1
        //
        // 5 × 3 = 15
        // =====================================================

        @(negedge clk);

        enable = 1'b1;

        a_in = 8'sd5;
        b_in = 8'sd3;

        @(negedge clk);

        $display("TEST 1");
        $display("A = %d", a_in);
        $display("B = %d", b_in);
        $display("ACC = %d", accumulator);

        if (accumulator == 32'sd15)
            $display("PASS");
        else
            $display("FAIL");


        // =====================================================
        // TEST 2
        //
        // 4 × 6 = 24
        //
        // Accumulator = 15 + 24 = 39
        // =====================================================

        a_in = 8'sd4;
        b_in = 8'sd6;

        @(negedge clk);

        $display("");
        $display("TEST 2");
        $display("ACC = %d", accumulator);

        if (accumulator == 32'sd39)
            $display("PASS");
        else
            $display("FAIL");


        // =====================================================
        // TEST 3
        //
        // -5 × 4 = -20
        //
        // 39 - 20 = 19
        // =====================================================

        a_in = -8'sd5;
        b_in = 8'sd4;

        @(negedge clk);

        $display("");
        $display("TEST 3 - SIGNED");
        $display("ACC = %d", accumulator);

        if (accumulator == 32'sd19)
            $display("PASS");
        else
            $display("FAIL");


        // =====================================================
        // TEST 4
        //
        // Check operand propagation
        // =====================================================

        a_in = 8'sd11;
        b_in = -8'sd2;

        @(negedge clk);

        #1;

        $display("");
        $display("TEST 4 - OPERAND PROPAGATION");
        $display("A OUT = %d", a_out);
        $display("B OUT = %d", b_out);

        if ((a_out == 8'sd11) &&
            (b_out == -8'sd2))
            $display("PASS");
        else
            $display("FAIL");


        // =====================================================
// TEST 5
//
// Disable PE
//
// Accumulator must not change
// =====================================================

enable = 1'b0;

a_in = 8'sd100;
b_in = 8'sd100;

@(negedge clk);

$display("");
$display("TEST 5 - DISABLE");
$display("ACC = %d", accumulator);

if (accumulator == -32'sd3)
    $display("PASS");
else
    $display("FAIL");


        // =====================================================
        // COMPLETE
        // =====================================================

        $display("");
        $display("========================================");
        $display("AI PE TEST COMPLETE");
        $display("========================================");

        #20;

        $finish;

    end


    // =========================================================
    // Waveform
    // =========================================================

    initial begin

        $dumpfile("ai_pe.vcd");

        $dumpvars(0,tb_ai_pe);

    end

endmodule

riscv_ai_accelerator.sim/sim_1/behav/xsim/ai_pe.vcd
$date
   Thu Aug 13 21:46:21 2026
$end

$version
  2026.1
  $dumpfile ("ai_pe.vcd") 
$end

$timescale
  1ps
$end

$scope module tb_ai_pe $end
$var reg 1 ! clk $end
$var reg 1 " rst $end
$var reg 1 # enable $end
$var reg 8 $ a_in [7:0] $end
$var reg 8 % b_in [7:0] $end
$var wire 8 & a_out [7:0] $end
$var wire 8 ' b_out [7:0] $end
$var wire 32 ( accumulator [31:0] $end
$scope module DUT $end
$var wire 1 ) clk $end
$var wire 1 * rst $end
$var wire 1 + enable $end
$var wire 8 , a_in [7:0] $end
$var wire 8 - b_in [7:0] $end
$var reg 8 . a_out [7:0] $end
$var reg 8 / b_out [7:0] $end
$var reg 32 0 accumulator [31:0] $end
$var reg 16 1 product [15:0] $end
$upscope $end
$upscope $end
$enddefinitions $end

#0
$dumpvars
0!
1"
0#
b0 $
b0 %
b0 &
b0 '
b0 (
0)
1*
0+
b0 ,
b0 -
b0 .
b0 /
b0 0
bx 1
$end

#5000
1!
1)

#10000
0!
0)

#15000
1!
1)

#20000
0!
0"
1#
b101 $
b11 %
0)
0*
1+
b101 ,
b11 -

#25000
1!
b101 &
b11 '
b1111 (
1)
b101 .
b11 /
b1111 0
b1111 1

#30000
0!
b100 $
b110 %
0)
b100 ,
b110 -

#35000
1!
b100 &
b110 '
b100111 (
1)
b100 .
b110 /
b100111 0
b11000 1

#40000
0!
b11111011 $
b100 %
0)
b11111011 ,
b100 -

#45000
1!
b11111011 &
b100 '
b10011 (
1)
b11111011 .
b100 /
b10011 0
b1111111111101100 1

#50000
0!
b1011 $
b11111110 %
0)
b1011 ,
b11111110 -

#55000
1!
b1011 &
b11111110 '
b11111111111111111111111111111101 (
1)
b1011 .
b11111110 /
b11111111111111111111111111111101 0
b1111111111101010 1

#60000
0!
0)

#61000
0#
b1100100 $
b1100100 %
0+
b1100100 ,
b1100100 -

