riscv_ai_accelerator.srcs/sources_1/new/ai_pe.v
`timescale 1ns/1ps

module ai_pe (

    input               clk,
    input               rst,

    input               enable,

    input signed [7:0]  a_in,
    input signed [7:0]  b_in,

    output reg signed [7:0]  a_out,
    output reg signed [7:0]  b_out,

    output reg signed [31:0] accumulator

);

    reg signed [15:0] product;


    always @(posedge clk or posedge rst) begin

        if (rst) begin

            a_out      <= 8'sd0;
            b_out      <= 8'sd0;

            accumulator <= 32'sd0;

        end

        else if (enable) begin

            // -------------------------------------------------
            // Pass operands to neighboring PE
            // -------------------------------------------------

            a_out <= a_in;

            b_out <= b_in;


            // -------------------------------------------------
            // INT8 multiplication
            // -------------------------------------------------

            product = a_in * b_in;


            // -------------------------------------------------
            // Accumulate
            // -------------------------------------------------

            accumulator <= accumulator + product;

        end

    end

endmodule

riscv_ai_accelerator.srcs/sources_1/new/ai_systolic_4x4.v
`timescale 1ns/1ps

module ai_systolic_4x4 (

    input clk,
    input rst,

    input enable,

    // =========================================================
    // Four 8-bit inputs for each row
    // =========================================================

    input signed [7:0] a0,
    input signed [7:0] a1,
    input signed [7:0] a2,
    input signed [7:0] a3,


    // =========================================================
    // Four 8-bit inputs for each column
    // =========================================================

    input signed [7:0] b0,
    input signed [7:0] b1,
    input signed [7:0] b2,
    input signed [7:0] b3,


    // =========================================================
    // 4 × 4 output matrix
    // =========================================================

    output signed [31:0] c00,
    output signed [31:0] c01,
    output signed [31:0] c02,
    output signed [31:0] c03,

    output signed [31:0] c10,
    output signed [31:0] c11,
    output signed [31:0] c12,
    output signed [31:0] c13,

    output signed [31:0] c20,
    output signed [31:0] c21,
    output signed [31:0] c22,
    output signed [31:0] c23,

    output signed [31:0] c30,
    output signed [31:0] c31,
    output signed [31:0] c32,
    output signed [31:0] c33

);


    // =========================================================
    // A operand propagation
    //
    // Horizontal movement
    // =========================================================

    wire signed [7:0] a00;
    wire signed [7:0] a01;
    wire signed [7:0] a02;
    wire signed [7:0] a03;

    wire signed [7:0] a10;
    wire signed [7:0] a11;
    wire signed [7:0] a12;
    wire signed [7:0] a13;

    wire signed [7:0] a20;
    wire signed [7:0] a21;
    wire signed [7:0] a22;
    wire signed [7:0] a23;

    wire signed [7:0] a30;
    wire signed [7:0] a31;
    wire signed [7:0] a32;
    wire signed [7:0] a33;


    // =========================================================
    // B operand propagation
    //
    // Vertical movement
    // =========================================================

    wire signed [7:0] b00;
    wire signed [7:0] b01;
    wire signed [7:0] b02;
    wire signed [7:0] b03;

    wire signed [7:0] b10;
    wire signed [7:0] b11;
    wire signed [7:0] b12;
    wire signed [7:0] b13;

    wire signed [7:0] b20;
    wire signed [7:0] b21;
    wire signed [7:0] b22;
    wire signed [7:0] b23;

    wire signed [7:0] b30;
    wire signed [7:0] b31;
    wire signed [7:0] b32;
    wire signed [7:0] b33;


    // =========================================================
    // PE00
    // =========================================================

    ai_pe PE00 (

        .clk(clk),
        .rst(rst),
        .enable(enable),

        .a_in(a0),
        .b_in(b0),

        .a_out(a00),
        .b_out(b00),

        .accumulator(c00)

    );


    // =========================================================
    // PE01
    // =========================================================

    ai_pe PE01 (

        .clk(clk),
        .rst(rst),
        .enable(enable),

        .a_in(a00),
        .b_in(b1),

        .a_out(a01),
        .b_out(b01),

        .accumulator(c01)

    );


    // =========================================================
    // PE02
    // =========================================================

    ai_pe PE02 (

        .clk(clk),
        .rst(rst),
        .enable(enable),

        .a_in(a01),
        .b_in(b2),

        .a_out(a02),
        .b_out(b02),

        .accumulator(c02)

    );


    // =========================================================
    // PE03
    // =========================================================

    ai_pe PE03 (

        .clk(clk),
        .rst(rst),
        .enable(enable),

        .a_in(a02),
        .b_in(b3),

        .a_out(a03),
        .b_out(b03),

        .accumulator(c03)

    );


    // =========================================================
    // PE10
    // =========================================================

    ai_pe PE10 (

        .clk(clk),
        .rst(rst),
        .enable(enable),

        .a_in(a1),
        .b_in(b00),

        .a_out(a10),
        .b_out(b10),

        .accumulator(c10)

    );


    // =========================================================
    // PE11
    // =========================================================

    ai_pe PE11 (

        .clk(clk),
        .rst(rst),
        .enable(enable),

        .a_in(a10),
        .b_in(b01),

        .a_out(a11),
        .b_out(b11),

        .accumulator(c11)

    );


    // =========================================================
    // PE12
    // =========================================================

    ai_pe PE12 (

        .clk(clk),
        .rst(rst),
        .enable(enable),

        .a_in(a11),
        .b_in(b02),

        .a_out(a12),
        .b_out(b12),

        .accumulator(c12)

    );


    // =========================================================
    // PE13
    // =========================================================

    ai_pe PE13 (

        .clk(clk),
        .rst(rst),
        .enable(enable),

        .a_in(a12),
        .b_in(b03),

        .a_out(a13),
        .b_out(b13),

        .accumulator(c13)

    );


    // =========================================================
    // PE20
    // =========================================================

    ai_pe PE20 (

        .clk(clk),
        .rst(rst),
        .enable(enable),

        .a_in(a2),
        .b_in(b10),

        .a_out(a20),
        .b_out(b20),

        .accumulator(c20)

    );


    // =========================================================
    // PE21
    // =========================================================

    ai_pe PE21 (

        .clk(clk),
        .rst(rst),
        .enable(enable),

        .a_in(a20),
        .b_in(b11),

        .a_out(a21),
        .b_out(b21),

        .accumulator(c21)

    );


    // =========================================================
    // PE22
    // =========================================================

    ai_pe PE22 (

        .clk(clk),
        .rst(rst),
        .enable(enable),

        .a_in(a21),
        .b_in(b12),

        .a_out(a22),
        .b_out(b22),

        .accumulator(c22)

    );


    // =========================================================
    // PE23
    // =========================================================

    ai_pe PE23 (

        .clk(clk),
        .rst(rst),
        .enable(enable),

        .a_in(a22),
        .b_in(b13),

        .a_out(a23),
        .b_out(b23),

        .accumulator(c23)

    );


    // =========================================================
    // PE30
    // =========================================================

    ai_pe PE30 (

        .clk(clk),
        .rst(rst),
        .enable(enable),

        .a_in(a3),
        .b_in(b20),

        .a_out(a30),
        .b_out(b30),

        .accumulator(c30)

    );


    // =========================================================
    // PE31
    // =========================================================

    ai_pe PE31 (

        .clk(clk),
        .rst(rst),
        .enable(enable),

        .a_in(a30),
        .b_in(b21),

        .a_out(a31),
        .b_out(b31),

        .accumulator(c31)

    );


    // =========================================================
    // PE32
    // =========================================================

    ai_pe PE32 (

        .clk(clk),
        .rst(rst),
        .enable(enable),

        .a_in(a31),
        .b_in(b22),

        .a_out(a32),
        .b_out(b32),

        .accumulator(c32)

    );


    // =========================================================
    // PE33
    // =========================================================

    ai_pe PE33 (

        .clk(clk),
        .rst(rst),
        .enable(enable),

        .a_in(a32),
        .b_in(b23),

        .a_out(a33),
        .b_out(b33),

        .accumulator(c33)

    );

endmodule

riscv_ai_accelerator.srcs/sim_1/new/tb_ai_systolic_4x4.v
`timescale 1ns/1ps

module tb_ai_systolic_4x4;

    reg clk;
    reg rst;
    reg enable;

    reg signed [7:0] a0;
    reg signed [7:0] a1;
    reg signed [7:0] a2;
    reg signed [7:0] a3;

    reg signed [7:0] b0;
    reg signed [7:0] b1;
    reg signed [7:0] b2;
    reg signed [7:0] b3;

    wire signed [31:0] c00;
    wire signed [31:0] c01;
    wire signed [31:0] c02;
    wire signed [31:0] c03;

    wire signed [31:0] c10;
    wire signed [31:0] c11;
    wire signed [31:0] c12;
    wire signed [31:0] c13;

    wire signed [31:0] c20;
    wire signed [31:0] c21;
    wire signed [31:0] c22;
    wire signed [31:0] c23;

    wire signed [31:0] c30;
    wire signed [31:0] c31;
    wire signed [31:0] c32;
    wire signed [31:0] c33;


    // =========================================================
    // DUT
    // =========================================================

    ai_systolic_4x4 DUT (

        .clk(clk),
        .rst(rst),
        .enable(enable),

        .a0(a0),
        .a1(a1),
        .a2(a2),
        .a3(a3),

        .b0(b0),
        .b1(b1),
        .b2(b2),
        .b3(b3),

        .c00(c00),
        .c01(c01),
        .c02(c02),
        .c03(c03),

        .c10(c10),
        .c11(c11),
        .c12(c12),
        .c13(c13),

        .c20(c20),
        .c21(c21),
        .c22(c22),
        .c23(c23),

        .c30(c30),
        .c31(c31),
        .c32(c32),
        .c33(c33)

    );


    // =========================================================
    // CLOCK
    // =========================================================

    initial begin

        clk = 1'b0;

        forever #5 clk = ~clk;

    end


    // =========================================================
    // DRIVE ONE CYCLE
    // =========================================================

    task drive_cycle;

        input signed [7:0] va0;
        input signed [7:0] va1;
        input signed [7:0] va2;
        input signed [7:0] va3;

        input signed [7:0] vb0;
        input signed [7:0] vb1;
        input signed [7:0] vb2;
        input signed [7:0] vb3;

        begin

            @(negedge clk);

            a0 = va0;
            a1 = va1;
            a2 = va2;
            a3 = va3;

            b0 = vb0;
            b1 = vb1;
            b2 = vb2;
            b3 = vb3;

        end

    endtask


    // =========================================================
    // TEST
    // =========================================================

    initial begin

        rst = 1'b1;
        enable = 1'b0;

        a0 = 0;
        a1 = 0;
        a2 = 0;
        a3 = 0;

        b0 = 0;
        b1 = 0;
        b2 = 0;
        b3 = 0;

        #20;

        rst = 1'b0;
        enable = 1'b1;


        // =====================================================
        // MATRIX A
        //
        //  1   2   3   4
        //  5   6   7   8
        //  9  10  11  12
        // 13  14  15  16
        //
        // MATRIX B = IDENTITY
        //
        // 1 0 0 0
        // 0 1 0 0
        // 0 0 1 0
        // 0 0 0 1
        //
        // A x B = A
        // =====================================================


        // =====================================================
        // t = 0
        //
        // A:
        // row0 -> A00 = 1
        //
        // B:
        // column0 -> B00 = 1
        // =====================================================

        drive_cycle(
            1, 0, 0, 0,
            1, 0, 0, 0
        );


        // =====================================================
        // t = 1
        //
        // A:
        // row0 -> A01 = 2
        // row1 -> A10 = 5
        //
        // B:
        // column0 -> B10 = 0
        // column1 -> B01 = 0
        // =====================================================

        drive_cycle(
            2, 5, 0, 0,
            0, 0, 0, 0
        );


        // =====================================================
        // t = 2
        //
        // A:
        // row0 -> A02 = 3
        // row1 -> A11 = 6
        // row2 -> A20 = 9
        //
        // B:
        // column0 -> B20 = 0
        // column1 -> B11 = 1
        // column2 -> B02 = 0
        // =====================================================

        drive_cycle(
            3, 6, 9, 0,
            0, 1, 0, 0
        );


        // =====================================================
        // t = 3
        //
        // A:
        // row0 -> A03 = 4
        // row1 -> A12 = 7
        // row2 -> A21 = 10
        // row3 -> A30 = 13
        //
        // B:
        // column0 -> B30 = 0
        // column1 -> B21 = 0
        // column2 -> B12 = 0
        // column3 -> B03 = 0
        // =====================================================

        drive_cycle(
            4, 7, 10, 13,
            0, 0, 0, 0
        );


        // =====================================================
        // t = 4
        //
        // A:
        // row1 -> A13 = 8
        // row2 -> A22 = 11
        // row3 -> A31 = 14
        //
        // B:
        // column1 -> B31 = 0
        // column2 -> B22 = 1
        // column3 -> B13 = 0
        // =====================================================

        drive_cycle(
            0, 8, 11, 14,
            0, 0, 1, 0
        );


        // =====================================================
        // t = 5
        //
        // A:
        // row2 -> A23 = 12
        // row3 -> A32 = 15
        //
        // B:
        // column2 -> B32 = 0
        // column3 -> B23 = 0
        // =====================================================

        drive_cycle(
            0, 0, 12, 15,
            0, 0, 0, 0
        );


        // =====================================================
        // t = 6
        //
        // A:
        // row3 -> A33 = 16
        //
        // B:
        // column3 -> B33 = 1
        // =====================================================

        drive_cycle(
            0, 0, 0, 16,
            0, 0, 0, 1
        );


        // =====================================================
        // Flush
        // =====================================================

        drive_cycle(
            0, 0, 0, 0,
            0, 0, 0, 0
        );

        drive_cycle(
            0, 0, 0, 0,
            0, 0, 0, 0
        );

        drive_cycle(
            0, 0, 0, 0,
            0, 0, 0, 0
        );


        @(negedge clk);

        enable = 1'b0;

        #2;


        // =====================================================
        // DISPLAY
        // =====================================================

        $display("");
        $display("========================================");
        $display("4x4 SYSTOLIC ARRAY RESULTS");
        $display("========================================");

        $display("");
        $display("C MATRIX:");

        $display("%d  %d  %d  %d",
                 c00, c01, c02, c03);

        $display("%d  %d  %d  %d",
                 c10, c11, c12, c13);

        $display("%d  %d  %d  %d",
                 c20, c21, c22, c23);

        $display("%d  %d  %d  %d",
                 c30, c31, c32, c33);


        // =====================================================
        // EXPECTED
        // =====================================================

        $display("");
        $display("EXPECTED:");

        $display(" 1   2   3   4");
        $display(" 5   6   7   8");
        $display(" 9  10  11  12");
        $display("13  14  15  16");


        // =====================================================
        // CHECK
        // =====================================================

        if ((c00 == 1)  &&
            (c01 == 2)  &&
            (c02 == 3)  &&
            (c03 == 4)  &&

            (c10 == 5)  &&
            (c11 == 6)  &&
            (c12 == 7)  &&
            (c13 == 8)  &&

            (c20 == 9)  &&
            (c21 == 10) &&
            (c22 == 11) &&
            (c23 == 12) &&

            (c30 == 13) &&
            (c31 == 14) &&
            (c32 == 15) &&
            (c33 == 16)) begin

            $display("");
            $display("========================================");
            $display("SYSTOLIC ARRAY TEST PASSED");
            $display("========================================");

        end

        else begin

            $display("");
            $display("========================================");
            $display("SYSTOLIC ARRAY TEST FAILED");
            $display("========================================");

        end


        #20;

        $finish;

    end


    // =========================================================
    // WAVEFORM
    // =========================================================

    initial begin

        $dumpfile("ai_systolic_4x4.vcd");

        $dumpvars(0, tb_ai_systolic_4x4);

    end

endmodule

riscv_ai_accelerator.sim/sim_1/behav/xsim/ai_systolic_4x4.vcd
$date
   Thu Aug 13 21:59:30 2026
$end

$version
  2026.1
  $dumpfile ("ai_systolic_4x4.vcd") 
$end

$timescale
  1ps
$end

$scope module tb_ai_systolic_4x4 $end
$var reg 1 ! clk $end
$var reg 1 " rst $end
$var reg 1 # enable $end
$var reg 8 $ a0 [7:0] $end
$var reg 8 % a1 [7:0] $end
$var reg 8 & a2 [7:0] $end
$var reg 8 ' a3 [7:0] $end
$var reg 8 ( b0 [7:0] $end
$var reg 8 ) b1 [7:0] $end
$var reg 8 * b2 [7:0] $end
$var reg 8 + b3 [7:0] $end
$var wire 32 , c00 [31:0] $end
$var wire 32 - c01 [31:0] $end
$var wire 32 . c02 [31:0] $end
$var wire 32 / c03 [31:0] $end
$var wire 32 0 c10 [31:0] $end
$var wire 32 1 c11 [31:0] $end
$var wire 32 2 c12 [31:0] $end
$var wire 32 3 c13 [31:0] $end
$var wire 32 4 c20 [31:0] $end
$var wire 32 5 c21 [31:0] $end
$var wire 32 6 c22 [31:0] $end
$var wire 32 7 c23 [31:0] $end
$var wire 32 8 c30 [31:0] $end
$var wire 32 9 c31 [31:0] $end
$var wire 32 : c32 [31:0] $end
$var wire 32 ; c33 [31:0] $end
$scope module DUT $end
$var wire 1 < clk $end
$var wire 1 = rst $end
$var wire 1 > enable $end
$var wire 8 ? a0 [7:0] $end
$var wire 8 @ a1 [7:0] $end
$var wire 8 A a2 [7:0] $end
$var wire 8 B a3 [7:0] $end
$var wire 8 C b0 [7:0] $end
$var wire 8 D b1 [7:0] $end
$var wire 8 E b2 [7:0] $end
$var wire 8 F b3 [7:0] $end
$var wire 32 , c00 [31:0] $end
$var wire 32 - c01 [31:0] $end
$var wire 32 . c02 [31:0] $end
$var wire 32 / c03 [31:0] $end
$var wire 32 0 c10 [31:0] $end
$var wire 32 1 c11 [31:0] $end
$var wire 32 2 c12 [31:0] $end
$var wire 32 3 c13 [31:0] $end
$var wire 32 4 c20 [31:0] $end
$var wire 32 5 c21 [31:0] $end
$var wire 32 6 c22 [31:0] $end
$var wire 32 7 c23 [31:0] $end
$var wire 32 8 c30 [31:0] $end
$var wire 32 9 c31 [31:0] $end
$var wire 32 : c32 [31:0] $end
$var wire 32 ; c33 [31:0] $end
$var wire 8 G a00 [7:0] $end
$var wire 8 H a01 [7:0] $end
$var wire 8 I a02 [7:0] $end
$var wire 8 J a03 [7:0] $end
$var wire 8 K a10 [7:0] $end
$var wire 8 L a11 [7:0] $end
$var wire 8 M a12 [7:0] $end
$var wire 8 N a13 [7:0] $end
$var wire 8 O a20 [7:0] $end
$var wire 8 P a21 [7:0] $end
$var wire 8 Q a22 [7:0] $end
$var wire 8 R a23 [7:0] $end
$var wire 8 S a30 [7:0] $end
$var wire 8 T a31 [7:0] $end
$var wire 8 U a32 [7:0] $end
$var wire 8 V a33 [7:0] $end
$var wire 8 W b00 [7:0] $end
$var wire 8 X b01 [7:0] $end
$var wire 8 Y b02 [7:0] $end
$var wire 8 Z b03 [7:0] $end
$var wire 8 [ b10 [7:0] $end
$var wire 8 \ b11 [7:0] $end
$var wire 8 ] b12 [7:0] $end
$var wire 8 ^ b13 [7:0] $end
$var wire 8 _ b20 [7:0] $end
$var wire 8 ` b21 [7:0] $end
$var wire 8 a b22 [7:0] $end
$var wire 8 b b23 [7:0] $end
$var wire 8 c b30 [7:0] $end
$var wire 8 d b31 [7:0] $end
$var wire 8 e b32 [7:0] $end
$var wire 8 f b33 [7:0] $end
$scope module PE00 $end
$var wire 1 < clk $end
$var wire 1 = rst $end
$var wire 1 > enable $end
$var wire 8 ? a_in [7:0] $end
$var wire 8 C b_in [7:0] $end
$var reg 8 g a_out [7:0] $end
$var reg 8 h b_out [7:0] $end
$var reg 32 i accumulator [31:0] $end
$var reg 16 j product [15:0] $end
$upscope $end
$scope module PE01 $end
$var wire 1 < clk $end
$var wire 1 = rst $end
$var wire 1 > enable $end
$var wire 8 G a_in [7:0] $end
$var wire 8 D b_in [7:0] $end
$var reg 8 k a_out [7:0] $end
$var reg 8 l b_out [7:0] $end
$var reg 32 m accumulator [31:0] $end
$var reg 16 n product [15:0] $end
$upscope $end
$scope module PE02 $end
$var wire 1 < clk $end
$var wire 1 = rst $end
$var wire 1 > enable $end
$var wire 8 H a_in [7:0] $end
$var wire 8 E b_in [7:0] $end
$var reg 8 o a_out [7:0] $end
$var reg 8 p b_out [7:0] $end
$var reg 32 q accumulator [31:0] $end
$var reg 16 r product [15:0] $end
$upscope $end
$scope module PE03 $end
$var wire 1 < clk $end
$var wire 1 = rst $end
$var wire 1 > enable $end
$var wire 8 I a_in [7:0] $end
$var wire 8 F b_in [7:0] $end
$var reg 8 s a_out [7:0] $end
$var reg 8 t b_out [7:0] $end
$var reg 32 u accumulator [31:0] $end
$var reg 16 v product [15:0] $end
$upscope $end
$scope module PE10 $end
$var wire 1 < clk $end
$var wire 1 = rst $end
$var wire 1 > enable $end
$var wire 8 @ a_in [7:0] $end
$var wire 8 W b_in [7:0] $end
$var reg 8 w a_out [7:0] $end
$var reg 8 x b_out [7:0] $end
$var reg 32 y accumulator [31:0] $end
$var reg 16 z product [15:0] $end
$upscope $end
$scope module PE11 $end
$var wire 1 < clk $end
$var wire 1 = rst $end
$var wire 1 > enable $end
$var wire 8 K a_in [7:0] $end
$var wire 8 X b_in [7:0] $end
$var reg 8 { a_out [7:0] $end
$var reg 8 | b_out [7:0] $end
$var reg 32 } accumulator [31:0] $end
$var reg 16 ~ product [15:0] $end
$upscope $end
$scope module PE12 $end
$var wire 1 < clk $end
$var wire 1 = rst $end
$var wire 1 > enable $end
$var wire 8 L a_in [7:0] $end
$var wire 8 Y b_in [7:0] $end
$var reg 8 !! a_out [7:0] $end
$var reg 8 "! b_out [7:0] $end
$var reg 32 #! accumulator [31:0] $end
$var reg 16 $! product [15:0] $end
$upscope $end
$scope module PE13 $end
$var wire 1 < clk $end
$var wire 1 = rst $end
$var wire 1 > enable $end
$var wire 8 M a_in [7:0] $end
$var wire 8 Z b_in [7:0] $end
$var reg 8 %! a_out [7:0] $end
$var reg 8 &! b_out [7:0] $end
$var reg 32 '! accumulator [31:0] $end
$var reg 16 (! product [15:0] $end
$upscope $end
$scope module PE20 $end
$var wire 1 < clk $end
$var wire 1 = rst $end
$var wire 1 > enable $end
$var wire 8 A a_in [7:0] $end
$var wire 8 [ b_in [7:0] $end
$var reg 8 )! a_out [7:0] $end
$var reg 8 *! b_out [7:0] $end
$var reg 32 +! accumulator [31:0] $end
$var reg 16 ,! product [15:0] $end
$upscope $end
$scope module PE21 $end
$var wire 1 < clk $end
$var wire 1 = rst $end
$var wire 1 > enable $end
$var wire 8 O a_in [7:0] $end
$var wire 8 \ b_in [7:0] $end
$var reg 8 -! a_out [7:0] $end
$var reg 8 .! b_out [7:0] $end
$var reg 32 /! accumulator [31:0] $end
$var reg 16 0! product [15:0] $end
$upscope $end
$scope module PE22 $end
$var wire 1 < clk $end
$var wire 1 = rst $end
$var wire 1 > enable $end
$var wire 8 P a_in [7:0] $end
$var wire 8 ] b_in [7:0] $end
$var reg 8 1! a_out [7:0] $end
$var reg 8 2! b_out [7:0] $end
$var reg 32 3! accumulator [31:0] $end
$var reg 16 4! product [15:0] $end
$upscope $end
$scope module PE23 $end
$var wire 1 < clk $end
$var wire 1 = rst $end
$var wire 1 > enable $end
$var wire 8 Q a_in [7:0] $end
$var wire 8 ^ b_in [7:0] $end
$var reg 8 5! a_out [7:0] $end
$var reg 8 6! b_out [7:0] $end
$var reg 32 7! accumulator [31:0] $end
$var reg 16 8! product [15:0] $end
$upscope $end
$scope module PE30 $end
$var wire 1 < clk $end
$var wire 1 = rst $end
$var wire 1 > enable $end
$var wire 8 B a_in [7:0] $end
$var wire 8 _ b_in [7:0] $end
$var reg 8 9! a_out [7:0] $end
$var reg 8 :! b_out [7:0] $end
$var reg 32 ;! accumulator [31:0] $end
$var reg 16 <! product [15:0] $end
$upscope $end
$scope module PE31 $end
$var wire 1 < clk $end
$var wire 1 = rst $end
$var wire 1 > enable $end
$var wire 8 S a_in [7:0] $end
$var wire 8 ` b_in [7:0] $end
$var reg 8 =! a_out [7:0] $end
$var reg 8 >! b_out [7:0] $end
$var reg 32 ?! accumulator [31:0] $end
$var reg 16 @! product [15:0] $end
$upscope $end
$scope module PE32 $end
$var wire 1 < clk $end
$var wire 1 = rst $end
$var wire 1 > enable $end
$var wire 8 T a_in [7:0] $end
$var wire 8 a b_in [7:0] $end
$var reg 8 A! a_out [7:0] $end
$var reg 8 B! b_out [7:0] $end
$var reg 32 C! accumulator [31:0] $end
$var reg 16 D! product [15:0] $end
$upscope $end
$scope module PE33 $end
$var wire 1 < clk $end
$var wire 1 = rst $end
$var wire 1 > enable $end
$var wire 8 U a_in [7:0] $end
$var wire 8 b b_in [7:0] $end
$var reg 8 E! a_out [7:0] $end
$var reg 8 F! b_out [7:0] $end
$var reg 32 G! accumulator [31:0] $end
$var reg 16 H! product [15:0] $end
$upscope $end
$upscope $end
$scope task drive_cycle $end
$var reg 8 I! va0 [7:0] $end
$var reg 8 J! va1 [7:0] $end
$var reg 8 K! va2 [7:0] $end
$var reg 8 L! va3 [7:0] $end
$var reg 8 M! vb0 [7:0] $end
$var reg 8 N! vb1 [7:0] $end
$var reg 8 O! vb2 [7:0] $end
$var reg 8 P! vb3 [7:0] $end
$upscope $end
$upscope $end
$enddefinitions $end

#0
$dumpvars
0!
b0 !!
1"
b0 "!
0#
b0 #!
b0 $
bx $!
b0 %
b0 %!
b0 &
b0 &!
b0 '
b0 '!
b0 (
bx (!
b0 )
b0 )!
b0 *
b0 *!
b0 +
b0 +!
b0 ,
bx ,!
b0 -
b0 -!
b0 .
b0 .!
b0 /
b0 /!
b0 0
bx 0!
b0 1
b0 1!
b0 2
b0 2!
b0 3
b0 3!
b0 4
bx 4!
b0 5
b0 5!
b0 6
b0 6!
b0 7
b0 7!
b0 8
bx 8!
b0 9
b0 9!
b0 :
b0 :!
b0 ;
b0 ;!
0<
bx <!
1=
b0 =!
0>
b0 >!
b0 ?
b0 ?!
b0 @
bx @!
b0 A
b0 A!
b0 B
b0 B!
b0 C
b0 C!
b0 D
bx D!
b0 E
b0 E!
b0 F
b0 F!
b0 G
b0 G!
b0 H
bx H!
b0 I
bx I!
b0 J
bx J!
b0 K
bx K!
b0 L
bx L!
b0 M
bx M!
b0 N
bx N!
b0 O
bx O!
b0 P
bx P!
b0 Q
b0 R
b0 S
b0 T
b0 U
b0 V
b0 W
b0 X
b0 Y
b0 Z
b0 [
b0 \
b0 ]
b0 ^
b0 _
b0 `
b0 a
b0 b
b0 c
b0 d
b0 e
b0 f
b0 g
b0 h
b0 i
bx j
b0 k
b0 l
b0 m
bx n
b0 o
b0 p
b0 q
bx r
b0 s
b0 t
b0 u
bx v
b0 w
b0 x
b0 y
bx z
b0 {
b0 |
b0 }
bx ~
$end

#5000
1!
1<

#10000
0!
0<

#15000
1!
1<

#20000
0!
0"
1#
b1 $
b1 (
0<
0=
1>
b1 ?
b1 C
b10 I!
b101 J!
b0 K!
b0 L!
b0 M!
b0 N!
b0 O!
b0 P!

#25000
1!
b0 $!
b0 (!
b1 ,
b0 ,!
b0 0!
b0 4!
b0 8!
1<
b0 <!
b0 @!
b0 D!
b1 G
b0 H!
b1 W
b1 g
b1 h
b1 i
b1 j
b0 n
b0 r
b0 v
b0 z
b0 ~

#30000
0!
b10 $
b101 %
b0 (
0<
b10 ?
b101 @
b0 C
b11 I!
b110 J!
b1001 K!
b1 N!

#35000
1!
b101 0
1<
b10 G
b1 H
b101 K
b0 W
b1 [
b10 g
b0 h
b0 j
b1 k
b101 w
b1 x
b101 y
b101 z

#40000
0!
b11 $
b110 %
b1001 &
b1 )
0<
b11 ?
b110 @
b1001 A
b1 D
b100 I!
b111 J!
b1010 K!
b1101 L!
b0 N!

#45000
1!
b1001 )!
b1 *!
b1001 +!
b1001 ,!
b10 -
b1001 4
1<
b11 G
b10 H
b1 I
b110 K
b101 L
b1001 O
b1 X
b0 [
b1 _
b11 g
b10 k
b1 l
b10 m
b10 n
b1 o
b110 w
b0 x
b0 z
b101 {

#50000
0!
b100 $
b111 %
b1010 &
b1101 '
b0 )
0<
b100 ?
b111 @
b1010 A
b1101 B
b0 D
b0 I!
b1000 J!
b1011 K!
b1110 L!
b1 O!

#55000
1!
b101 !!
b1010 )!
b0 *!
b0 ,!
b1001 -!
b110 1
b1101 8
b1101 9!
b1 :!
b1101 ;!
1<
b1101 <!
b100 G
b11 H
b10 I
b1 J
b111 K
b110 L
b101 M
b1010 O
b1001 P
b1101 S
b0 X
b1 \
b0 _
b1 c
b100 g
b11 k
b0 l
b0 n
b10 o
b1 s
b111 w
b110 {
b1 |
b110 }
b110 ~

#60000
0!
b0 $
b1000 %
b1011 &
b1110 '
b1 *
0<
b0 ?
b1000 @
b1011 A
b1110 B
b1 E
b0 J!
b1100 K!
b1111 L!
b0 O!

#65000
1!
b110 !!
b101 %!
b1011 )!
b1010 -!
b11 .
b1 .!
b1010 /!
b1010 0!
b1001 1!
b1010 5
b1110 9!
b0 :!
1<
b0 <!
b1101 =!
b0 G
b100 H
b11 I
b10 J
b1000 K
b111 L
b110 M
b101 N
b1011 O
b1010 P
b1001 Q
b1110 S
b1101 T
b1 Y
b0 \
b1 `
b0 c
b0 g
b100 k
b11 o
b1 p
b11 q
b11 r
b10 s
b1000 w
b111 {
b0 |
b0 ~

#70000
0!
b0 %
b1100 &
b1111 '
b0 *
0<
b0 @
b1100 A
b1111 B
b0 E
b0 K!
b10000 L!
b1 P!

#75000
1!
b111 !!
b1 "!
b111 #!
b111 $!
b110 %!
b1100 )!
b1011 -!
b0 .!
b0 0!
b1010 1!
b111 2
b1001 5!
b1110 9
b1111 9!
1<
b1110 =!
b1 >!
b1110 ?!
b1110 @!
b1101 A!
b0 H
b100 I
b11 J
b0 K
b1000 L
b111 M
b110 N
b1100 O
b1011 P
b1010 Q
b1001 R
b1111 S
b1110 T
b1101 U
b0 Y
b1 ]
b0 `
b1 d
b0 k
b100 o
b0 p
b0 r
b11 s
b0 w
b1000 {

#80000
0!
b0 &
b10000 '
b1 +
0<
b0 A
b10000 B
b1 F
b0 L!
b0 P!

#85000
1!
b1000 !!
b0 "!
b0 $!
b111 %!
b0 )!
b1100 -!
b100 /
b1011 1!
b1 2!
b1011 3!
b1011 4!
b1010 5!
b1011 6
b10000 9!
1<
b1111 =!
b0 >!
b0 @!
b1110 A!
b1101 E!
b0 I
b100 J
b0 L
b1000 M
b111 N
b0 O
b1100 P
b1011 Q
b1010 R
b10000 S
b1111 T
b1110 U
b1101 V
b1 Z
b0 ]
b1 a
b0 d
b0 o
b100 s
b1 t
b100 u
b100 v
b0 {

#90000
0!
b0 '
b0 +
0<
b0 B
b0 F

#95000
1!
b0 !!
b1000 %!
b1 &!
b1000 '!
b1000 (!
b0 -!
b1100 1!
b0 2!
b1000 3
b0 4!
b1011 5!
b0 9!
b1111 :
1<
b10000 =!
b1111 A!
b1 B!
b1111 C!
b1111 D!
b1110 E!
b0 J
b0 M
b1000 N
b0 P
b1100 Q
b1011 R
b0 S
b10000 T
b1111 U
b1110 V
b0 Z
b1 ^
b0 a
b1 e
b0 s
b0 t
b0 v

#100000
0!
0<

#105000
1!
b0 %!
b0 &!
b0 (!
b0 1!
b1100 5!
b1 6!
b1100 7
b1100 7!
b1100 8!
1<
b0 =!
b10000 A!
b0 B!
b0 D!
b1111 E!
b0 N
b0 Q
b1100 R
b0 T
b10000 U
b1111 V
b0 ^
b1 b
b0 e

#110000
0!
0<

#115000
1!
b0 5!
b0 6!
b0 8!
b10000 ;
1<
b0 A!
b10000 E!
b1 F!
b10000 G!
b10000 H!
b0 R
b0 U
b10000 V
b0 b
b1 f

#120000
0!
0#
0<
0>

