riscv_ai_accelerator.srcs/sources_1/new/ai_stream_controller.v
`timescale 1ns/1ps

module ai_stream_controller (

    input clk,
    input rst,

    // =========================================================
    // CONTROL
    // =========================================================

    input start,

    output reg busy,
    output reg done,


    // =========================================================
    // MATRIX A
    //
    // Each 32-bit word:
    //
    // [31:24] = column 3
    // [23:16] = column 2
    // [15:8]  = column 1
    // [7:0]   = column 0
    // =========================================================

    input [31:0] matrix_a0,
    input [31:0] matrix_a1,
    input [31:0] matrix_a2,
    input [31:0] matrix_a3,


    // =========================================================
    // MATRIX B
    //
    // Each 32-bit word represents one ROW of B.
    // =========================================================

    input [31:0] matrix_b0,
    input [31:0] matrix_b1,
    input [31:0] matrix_b2,
    input [31:0] matrix_b3,


    // =========================================================
    // A STREAM
    // =========================================================

    output reg signed [7:0] a0,
    output reg signed [7:0] a1,
    output reg signed [7:0] a2,
    output reg signed [7:0] a3,


    // =========================================================
    // B STREAM
    // =========================================================

    output reg signed [7:0] b0,
    output reg signed [7:0] b1,
    output reg signed [7:0] b2,
    output reg signed [7:0] b3,


    // =========================================================
    // SYSTOLIC ENABLE
    // =========================================================

    output reg compute_enable

);


    // =========================================================
    // STATES
    // =========================================================

    localparam STATE_IDLE  = 2'b00;
    localparam STATE_STREAM = 2'b01;
    localparam STATE_FLUSH = 2'b10;
    localparam STATE_DONE  = 2'b11;


    reg [1:0] state;

    reg [3:0] cycle;


    // =========================================================
    // STORED MATRIX VALUES
    // =========================================================

    reg [31:0] A0_reg;
    reg [31:0] A1_reg;
    reg [31:0] A2_reg;
    reg [31:0] A3_reg;

    reg [31:0] B0_reg;
    reg [31:0] B1_reg;
    reg [31:0] B2_reg;
    reg [31:0] B3_reg;


    // =========================================================
    // SEQUENTIAL FSM
    // =========================================================

    always @(posedge clk or posedge rst) begin

        if (rst) begin

            state <= STATE_IDLE;

            cycle <= 4'd0;

            A0_reg <= 32'd0;
            A1_reg <= 32'd0;
            A2_reg <= 32'd0;
            A3_reg <= 32'd0;

            B0_reg <= 32'd0;
            B1_reg <= 32'd0;
            B2_reg <= 32'd0;
            B3_reg <= 32'd0;

        end

        else begin

            case (state)

                // =================================================
                // IDLE
                // =================================================

                STATE_IDLE: begin

                    cycle <= 4'd0;

                    if (start) begin

                        A0_reg <= matrix_a0;
                        A1_reg <= matrix_a1;
                        A2_reg <= matrix_a2;
                        A3_reg <= matrix_a3;

                        B0_reg <= matrix_b0;
                        B1_reg <= matrix_b1;
                        B2_reg <= matrix_b2;
                        B3_reg <= matrix_b3;

                        state <= STATE_STREAM;

                    end

                end


                // =================================================
                // STREAM
                //
                // Seven cycles:
                //
                // 0 1 2 3 4 5 6
                // =================================================

                STATE_STREAM: begin

                    if (cycle == 4'd6) begin

                        cycle <= 4'd0;

                        state <= STATE_FLUSH;

                    end

                    else begin

                        cycle <= cycle + 1'b1;

                    end

                end


                // =================================================
                // FLUSH
                // =================================================

                STATE_FLUSH: begin

                    if (cycle == 4'd2) begin

                        cycle <= 4'd0;

                        state <= STATE_DONE;

                    end

                    else begin

                        cycle <= cycle + 1'b1;

                    end

                end


                // =================================================
                // DONE
                // =================================================

                STATE_DONE: begin

                    state <= STATE_IDLE;

                    cycle <= 4'd0;

                end


                default: begin

                    state <= STATE_IDLE;

                    cycle <= 4'd0;

                end

            endcase

        end

    end


    // =========================================================
    // COMBINATIONAL OUTPUT LOGIC
    // =========================================================

    always @(*) begin

        // =====================================================
        // DEFAULTS
        // =====================================================

        busy = 1'b0;

        done = 1'b0;

        compute_enable = 1'b0;

        a0 = 8'sd0;
        a1 = 8'sd0;
        a2 = 8'sd0;
        a3 = 8'sd0;

        b0 = 8'sd0;
        b1 = 8'sd0;
        b2 = 8'sd0;
        b3 = 8'sd0;


        case (state)

            // =================================================
            // IDLE
            // =================================================

            STATE_IDLE: begin

                busy = 1'b0;

            end


            // =================================================
            // STREAM
            // =================================================

            STATE_STREAM: begin

                busy = 1'b1;

                compute_enable = 1'b1;


                case (cycle)

                    // =================================================
                    // CYCLE 0
                    //
                    // A:
                    //
                    // 1
                    //
                    // B:
                    //
                    // B00
                    // =================================================

                    4'd0: begin

                        a0 = A0_reg[7:0];

                        a1 = 0;
                        a2 = 0;
                        a3 = 0;


                        b0 = B0_reg[7:0];

                        b1 = 0;
                        b2 = 0;
                        b3 = 0;

                    end


                    // =================================================
                    // CYCLE 1
                    //
                    // A:
                    //
                    // A01
                    // A10
                    //
                    // B:
                    //
                    // B10
                    // B01
                    // =================================================

                    4'd1: begin

                        a0 = A0_reg[15:8];

                        a1 = A1_reg[7:0];

                        a2 = 0;
                        a3 = 0;


                        b0 = B1_reg[7:0];

                        b1 = B0_reg[15:8];

                        b2 = 0;
                        b3 = 0;

                    end


                    // =================================================
                    // CYCLE 2
                    //
                    // A:
                    //
                    // A02
                    // A11
                    // A20
                    //
                    // B:
                    //
                    // B20
                    // B11
                    // B02
                    // =================================================

                    4'd2: begin

                        a0 = A0_reg[23:16];

                        a1 = A1_reg[15:8];

                        a2 = A2_reg[7:0];

                        a3 = 0;


                        b0 = B2_reg[7:0];

                        b1 = B1_reg[15:8];

                        b2 = B0_reg[23:16];

                        b3 = 0;

                    end


                    // =================================================
                    // CYCLE 3
                    //
                    // A:
                    //
                    // A03
                    // A12
                    // A21
                    // A30
                    //
                    // B:
                    //
                    // B30
                    // B21
                    // B12
                    // B03
                    // =================================================

                    4'd3: begin

                        a0 = A0_reg[31:24];

                        a1 = A1_reg[23:16];

                        a2 = A2_reg[15:8];

                        a3 = A3_reg[7:0];


                        b0 = B3_reg[7:0];

                        b1 = B2_reg[15:8];

                        b2 = B1_reg[23:16];

                        b3 = B0_reg[31:24];

                    end


                    // =================================================
                    // CYCLE 4
                    //
                    // A:
                    //
                    // A13
                    // A22
                    // A31
                    //
                    // B:
                    //
                    // B31
                    // B22
                    // B13
                    // =================================================

                    4'd4: begin

                        a0 = 0;

                        a1 = A1_reg[31:24];

                        a2 = A2_reg[23:16];

                        a3 = A3_reg[15:8];


                        b0 = 0;

                        b1 = B3_reg[15:8];

                        b2 = B2_reg[23:16];

                        b3 = B1_reg[31:24];

                    end


                    // =================================================
                    // CYCLE 5
                    //
                    // A:
                    //
                    // A23
                    // A32
                    //
                    // B:
                    //
                    // B32
                    // B23
                    // =================================================

                    4'd5: begin

                        a0 = 0;
                        a1 = 0;

                        a2 = A2_reg[31:24];

                        a3 = A3_reg[23:16];


                        b0 = 0;
                        b1 = 0;

                        b2 = B3_reg[23:16];

                        b3 = B2_reg[31:24];

                    end


                    // =================================================
                    // CYCLE 6
                    //
                    // A:
                    //
                    // A33
                    //
                    // B:
                    //
                    // B33
                    // =================================================

                    4'd6: begin

                        a0 = 0;
                        a1 = 0;
                        a2 = 0;

                        a3 = A3_reg[31:24];


                        b0 = 0;
                        b1 = 0;
                        b2 = 0;

                        b3 = B3_reg[31:24];

                    end


                    default: begin

                        a0 = 0;
                        a1 = 0;
                        a2 = 0;
                        a3 = 0;

                        b0 = 0;
                        b1 = 0;
                        b2 = 0;
                        b3 = 0;

                    end

                endcase

            end


            // =================================================
            // FLUSH
            // =================================================

            STATE_FLUSH: begin

                busy = 1'b1;

                compute_enable = 1'b1;

                a0 = 0;
                a1 = 0;
                a2 = 0;
                a3 = 0;

                b0 = 0;
                b1 = 0;
                b2 = 0;
                b3 = 0;

            end


            // =================================================
            // DONE
            // =================================================

            STATE_DONE: begin

                busy = 1'b0;

                done = 1'b1;

            end


            default: begin

                busy = 1'b0;

                done = 1'b0;

            end

        endcase

    end

endmodule

riscv_ai_accelerator.srcs/sim_1/new/tb_ai_stream_controller.v
`timescale 1ns/1ps

module tb_ai_stream_controller;

    reg clk;
    reg rst;
    reg start;

    reg [31:0] matrix_a0;
    reg [31:0] matrix_a1;
    reg [31:0] matrix_a2;
    reg [31:0] matrix_a3;

    reg [31:0] matrix_b0;
    reg [31:0] matrix_b1;
    reg [31:0] matrix_b2;
    reg [31:0] matrix_b3;

    wire busy;
    wire done;

    wire signed [7:0] a0;
    wire signed [7:0] a1;
    wire signed [7:0] a2;
    wire signed [7:0] a3;

    wire signed [7:0] b0;
    wire signed [7:0] b1;
    wire signed [7:0] b2;
    wire signed [7:0] b3;

    wire compute_enable;


    // =========================================================
    // DUT
    // =========================================================

    ai_stream_controller DUT (

        .clk(clk),
        .rst(rst),

        .start(start),

        .busy(busy),
        .done(done),

        .matrix_a0(matrix_a0),
        .matrix_a1(matrix_a1),
        .matrix_a2(matrix_a2),
        .matrix_a3(matrix_a3),

        .matrix_b0(matrix_b0),
        .matrix_b1(matrix_b1),
        .matrix_b2(matrix_b2),
        .matrix_b3(matrix_b3),

        .a0(a0),
        .a1(a1),
        .a2(a2),
        .a3(a3),

        .b0(b0),
        .b1(b1),
        .b2(b2),
        .b3(b3),

        .compute_enable(compute_enable)

    );


    // =========================================================
    // CLOCK
    // =========================================================

    initial begin

        clk = 1'b0;

        forever #5 clk = ~clk;

    end


    // =========================================================
    // TEST
    // =========================================================

    initial begin

        rst = 1'b1;
        start = 1'b0;


        // =====================================================
        // MATRIX A
        //
        //  1   2   3   4
        //  5   6   7   8
        //  9  10  11  12
        // 13  14  15  16
        // =====================================================

        matrix_a0 = {8'd4,  8'd3,  8'd2,  8'd1};
        matrix_a1 = {8'd8,  8'd7,  8'd6,  8'd5};
        matrix_a2 = {8'd12, 8'd11, 8'd10, 8'd9};
        matrix_a3 = {8'd16, 8'd15, 8'd14, 8'd13};


        // =====================================================
        // MATRIX B
        //
        //  1   2   1   0
        //  0   1   2   1
        //  1   0   1   2
        //  2   1   0   1
        //
        // Rows are packed into 32-bit words.
        // =====================================================

        matrix_b0 = {8'd0, 8'd1, 8'd2, 8'd1};

        matrix_b1 = {8'd1, 8'd2, 8'd1, 8'd0};

        matrix_b2 = {8'd2, 8'd1, 8'd0, 8'd1};

        matrix_b3 = {8'd1, 8'd0, 8'd1, 8'd2};


        // =====================================================
        // RESET
        // =====================================================

        #20;

        rst = 1'b0;


        // =====================================================
        // START
        // =====================================================

        @(negedge clk);

        start = 1'b1;

        @(negedge clk);

        start = 1'b0;


        // =====================================================
        // MONITOR EVERY STREAM CYCLE
        // =====================================================

        repeat (12) begin

            @(negedge clk);

            $display(
                "cycle=%d | busy=%b | compute=%b | A=(%d,%d,%d,%d) | B=(%d,%d,%d,%d)",
                DUT.cycle,
                busy,
                compute_enable,
                a0,a1,a2,a3,
                b0,b1,b2,b3
            );

        end


        // =====================================================
        // WAIT FOR DONE
        // =====================================================

        wait(done);

        #1;


        $display("");
        $display("========================================");
        $display("AI STREAM CONTROLLER TEST COMPLETE");
        $display("========================================");

        if (done)
            $display("DONE = PASS");
        else
            $display("DONE = FAIL");


        #20;

        $finish;

    end


    // =========================================================
    // WAVEFORM
    // =========================================================

    initial begin

        $dumpfile("ai_stream_controller.vcd");

        $dumpvars(0,tb_ai_stream_controller);

    end

endmodule

riscv_ai_accelerator.sim/sim_1/behav/xsim/ai_stream_controller.vcd
$date
   Fri Aug 14 10:49:29 2026
$end

$version
  2026.1
  $dumpfile ("ai_stream_controller.vcd") 
$end

$timescale
  1ps
$end

$scope module tb_ai_stream_controller $end
$var reg 1 ! clk $end
$var reg 1 " rst $end
$var reg 1 # start $end
$var reg 32 $ matrix_a0 [31:0] $end
$var reg 32 % matrix_a1 [31:0] $end
$var reg 32 & matrix_a2 [31:0] $end
$var reg 32 ' matrix_a3 [31:0] $end
$var reg 32 ( matrix_b0 [31:0] $end
$var reg 32 ) matrix_b1 [31:0] $end
$var reg 32 * matrix_b2 [31:0] $end
$var reg 32 + matrix_b3 [31:0] $end
$var wire 1 , busy $end
$var wire 1 - done $end
$var wire 8 . a0 [7:0] $end
$var wire 8 / a1 [7:0] $end
$var wire 8 0 a2 [7:0] $end
$var wire 8 1 a3 [7:0] $end
$var wire 8 2 b0 [7:0] $end
$var wire 8 3 b1 [7:0] $end
$var wire 8 4 b2 [7:0] $end
$var wire 8 5 b3 [7:0] $end
$var wire 1 6 compute_enable $end
$scope module DUT $end
$var wire 1 7 clk $end
$var wire 1 8 rst $end
$var wire 1 9 start $end
$var reg 1 : busy $end
$var reg 1 ; done $end
$var wire 32 < matrix_a0 [31:0] $end
$var wire 32 = matrix_a1 [31:0] $end
$var wire 32 > matrix_a2 [31:0] $end
$var wire 32 ? matrix_a3 [31:0] $end
$var wire 32 @ matrix_b0 [31:0] $end
$var wire 32 A matrix_b1 [31:0] $end
$var wire 32 B matrix_b2 [31:0] $end
$var wire 32 C matrix_b3 [31:0] $end
$var reg 8 D a0 [7:0] $end
$var reg 8 E a1 [7:0] $end
$var reg 8 F a2 [7:0] $end
$var reg 8 G a3 [7:0] $end
$var reg 8 H b0 [7:0] $end
$var reg 8 I b1 [7:0] $end
$var reg 8 J b2 [7:0] $end
$var reg 8 K b3 [7:0] $end
$var reg 1 L compute_enable $end
$var reg 2 M state [1:0] $end
$var reg 4 N cycle [3:0] $end
$var reg 32 O A0_reg [31:0] $end
$var reg 32 P A1_reg [31:0] $end
$var reg 32 Q A2_reg [31:0] $end
$var reg 32 R A3_reg [31:0] $end
$var reg 32 S B0_reg [31:0] $end
$var reg 32 T B1_reg [31:0] $end
$var reg 32 U B2_reg [31:0] $end
$var reg 32 V B3_reg [31:0] $end
$upscope $end
$upscope $end
$enddefinitions $end

#0
$dumpvars
0!
1"
0#
b100000000110000001000000001 $
b1000000001110000011000000101 %
b1100000010110000101000001001 &
b10000000011110000111000001101 '
b10000001000000001 (
b1000000100000000100000000 )
b10000000010000000000000001 *
b1000000000000000100000010 +
0,
0-
b0 .
b0 /
b0 0
b0 1
b0 2
b0 3
b0 4
b0 5
06
07
18
09
0:
0;
b100000000110000001000000001 <
b1000000001110000011000000101 =
b1100000010110000101000001001 >
b10000000011110000111000001101 ?
b10000001000000001 @
b1000000100000000100000000 A
b10000000010000000000000001 B
b1000000000000000100000010 C
b0 D
b0 E
b0 F
b0 G
b0 H
b0 I
b0 J
b0 K
0L
b0 M
b0 N
b0 O
b0 P
b0 Q
b0 R
b0 S
b0 T
b0 U
b0 V
$end

#5000
1!
17

#10000
0!
07

#15000
1!
17

#20000
0!
0"
1#
07
08
19

#25000
1!
1,
b1 .
b1 2
16
17
1:
b1 D
b1 H
1L
b1 M
b100000000110000001000000001 O
b1000000001110000011000000101 P
b1100000010110000101000001001 Q
b10000000011110000111000001101 R
b10000001000000001 S
b1000000100000000100000000 T
b10000000010000000000000001 U
b1000000000000000100000010 V

#30000
0!
0#
07
09

#35000
1!
b10 .
b101 /
b0 2
b10 3
17
1:
b10 D
b101 E
b0 H
b10 I
1L
b1 N

#40000
0!
07

#45000
1!
b11 .
b110 /
b1001 0
b1 2
b1 3
b1 4
17
1:
b11 D
b110 E
b1001 F
b1 H
b1 I
b1 J
1L
b10 N

#50000
0!
07

#55000
1!
b100 .
b111 /
b1010 0
b1101 1
b10 2
b0 3
b10 4
17
1:
b100 D
b111 E
b1010 F
b1101 G
b10 H
b0 I
b10 J
1L
b11 N

#60000
0!
07

#65000
1!
b0 .
b1000 /
b1011 0
b1110 1
b0 2
b1 3
b1 4
b1 5
17
1:
b0 D
b1000 E
b1011 F
b1110 G
b0 H
b1 I
b1 J
b1 K
1L
b100 N

#70000
0!
07

#75000
1!
b0 /
b1100 0
b1111 1
b0 3
b0 4
b10 5
17
1:
b0 E
b1100 F
b1111 G
b0 I
b0 J
b10 K
1L
b101 N

#80000
0!
07

#85000
1!
b0 0
b10000 1
b1 5
17
1:
b0 F
b10000 G
b1 K
1L
b110 N

#90000
0!
07

#95000
1!
b0 1
b0 5
17
1:
b0 G
b0 K
1L
b10 M
b0 N

#100000
0!
07

#105000
1!
17
1:
1L
b1 N

#110000
0!
07

#115000
1!
17
1:
1L
b10 N

#120000
0!
07

#125000
1!
0,
1-
06
17
0:
1;
0L
b11 M
b0 N

#130000
0!
07

#135000
1!
0-
17
0;
b0 M

