riscv_ai_accelerator.srcs/sources_1/new/riscv_forwarding.v
`timescale 1ns/1ps

module riscv_forwarding (

    input      [4:0] idex_rs1,
    input      [4:0] idex_rs2,

    input      [4:0] exmem_rd,
    input             exmem_regwrite,

    input      [4:0] memwb_rd,
    input             memwb_regwrite,

    output reg [1:0] forward_a,
    output reg [1:0] forward_b

);

    // =========================================================
    // Forwarding selection
    //
    // 00 = Register File
    // 01 = MEM/WB
    // 10 = EX/MEM
    // =========================================================

    always @(*) begin

        // -----------------------------------------------------
        // Default
        // -----------------------------------------------------

        forward_a = 2'b00;
        forward_b = 2'b00;


        // =====================================================
        // Forward A
        // =====================================================

        if (exmem_regwrite &&
            (exmem_rd != 5'd0) &&
            (exmem_rd == idex_rs1)) begin

            forward_a = 2'b10;

        end

        else if (memwb_regwrite &&
                 (memwb_rd != 5'd0) &&
                 (memwb_rd == idex_rs1)) begin

            forward_a = 2'b01;

        end


        // =====================================================
        // Forward B
        // =====================================================

        if (exmem_regwrite &&
            (exmem_rd != 5'd0) &&
            (exmem_rd == idex_rs2)) begin

            forward_b = 2'b10;

        end

        else if (memwb_regwrite &&
                 (memwb_rd != 5'd0) &&
                 (memwb_rd == idex_rs2)) begin

            forward_b = 2'b01;

        end

    end

endmodule

riscv_ai_accelerator.srcs/sim_1/new/tb_riscv_forwarding.v
`timescale 1ns/1ps

module tb_riscv_forwarding;

    reg [4:0] idex_rs1;
    reg [4:0] idex_rs2;

    reg [4:0] exmem_rd;
    reg       exmem_regwrite;

    reg [4:0] memwb_rd;
    reg       memwb_regwrite;

    wire [1:0] forward_a;
    wire [1:0] forward_b;


    // =========================================================
    // DUT
    // =========================================================

    riscv_forwarding DUT (

        .idex_rs1(idex_rs1),
        .idex_rs2(idex_rs2),

        .exmem_rd(exmem_rd),
        .exmem_regwrite(exmem_regwrite),

        .memwb_rd(memwb_rd),
        .memwb_regwrite(memwb_regwrite),

        .forward_a(forward_a),
        .forward_b(forward_b)

    );


    // =========================================================
    // Test
    // =========================================================

    initial begin

        $display("========================================");
        $display("RISC-V FORWARDING UNIT TEST");
        $display("========================================");


        // =====================================================
        // TEST 1
        //
        // No dependency
        // =====================================================

        idex_rs1 = 5'd1;
        idex_rs2 = 5'd2;

        exmem_rd = 5'd3;
        exmem_regwrite = 1'b1;

        memwb_rd = 5'd4;
        memwb_regwrite = 1'b1;

        #10;

        $display("");
        $display("TEST 1 - NO DEPENDENCY");
        $display("Forward A = %b",forward_a);
        $display("Forward B = %b",forward_b);

        if ((forward_a == 2'b00) &&
            (forward_b == 2'b00))
            $display("PASS");
        else
            $display("FAIL");


        // =====================================================
        // TEST 2
        //
        // rs1 depends on EX/MEM
        // =====================================================

        idex_rs1 = 5'd5;
        idex_rs2 = 5'd2;

        exmem_rd = 5'd5;
        exmem_regwrite = 1'b1;

        memwb_rd = 5'd4;
        memwb_regwrite = 1'b1;

        #10;

        $display("");
        $display("TEST 2 - EX/MEM -> RS1");
        $display("Forward A = %b",forward_a);

        if (forward_a == 2'b10)
            $display("PASS");
        else
            $display("FAIL");


        // =====================================================
        // TEST 3
        //
        // rs2 depends on EX/MEM
        // =====================================================

        idex_rs1 = 5'd1;
        idex_rs2 = 5'd6;

        exmem_rd = 5'd6;
        exmem_regwrite = 1'b1;

        memwb_rd = 5'd4;
        memwb_regwrite = 1'b1;

        #10;

        $display("");
        $display("TEST 3 - EX/MEM -> RS2");
        $display("Forward B = %b",forward_b);

        if (forward_b == 2'b10)
            $display("PASS");
        else
            $display("FAIL");


        // =====================================================
        // TEST 4
        //
        // rs1 depends on MEM/WB
        // =====================================================

        idex_rs1 = 5'd7;
        idex_rs2 = 5'd2;

        exmem_rd = 5'd4;
        exmem_regwrite = 1'b1;

        memwb_rd = 5'd7;
        memwb_regwrite = 1'b1;

        #10;

        $display("");
        $display("TEST 4 - MEM/WB -> RS1");
        $display("Forward A = %b",forward_a);

        if (forward_a == 2'b01)
            $display("PASS");
        else
            $display("FAIL");


        // =====================================================
        // TEST 5
        //
        // rs2 depends on MEM/WB
        // =====================================================

        idex_rs1 = 5'd1;
        idex_rs2 = 5'd8;

        exmem_rd = 5'd4;
        exmem_regwrite = 1'b1;

        memwb_rd = 5'd8;
        memwb_regwrite = 1'b1;

        #10;

        $display("");
        $display("TEST 5 - MEM/WB -> RS2");
        $display("Forward B = %b",forward_b);

        if (forward_b == 2'b01)
            $display("PASS");
        else
            $display("FAIL");


        // =====================================================
        // TEST 6
        //
        // Both operands forwarded from EX/MEM
        // =====================================================

        idex_rs1 = 5'd10;
        idex_rs2 = 5'd11;

        exmem_rd = 5'd10;
        exmem_regwrite = 1'b1;

        memwb_rd = 5'd11;
        memwb_regwrite = 1'b1;

        #10;

        $display("");
        $display("TEST 6 - BOTH OPERANDS");
        $display("Forward A = %b",forward_a);
        $display("Forward B = %b",forward_b);

        if ((forward_a == 2'b10) &&
            (forward_b == 2'b01))
            $display("PASS");
        else
            $display("FAIL");


        // =====================================================
        // TEST 7
        //
        // EX/MEM has priority over MEM/WB
        //
        // Both produce x12
        // =====================================================

        idex_rs1 = 5'd12;
        idex_rs2 = 5'd2;

        exmem_rd = 5'd12;
        exmem_regwrite = 1'b1;

        memwb_rd = 5'd12;
        memwb_regwrite = 1'b1;

        #10;

        $display("");
        $display("TEST 7 - EX/MEM PRIORITY");
        $display("Forward A = %b",forward_a);

        if (forward_a == 2'b10)
            $display("PASS");
        else
            $display("FAIL");


        // =====================================================
        // TEST 8
        //
        // x0 must never be forwarded
        // =====================================================

        idex_rs1 = 5'd0;
        idex_rs2 = 5'd0;

        exmem_rd = 5'd0;
        exmem_regwrite = 1'b1;

        memwb_rd = 5'd0;
        memwb_regwrite = 1'b1;

        #10;

        $display("");
        $display("TEST 8 - x0");
        $display("Forward A = %b",forward_a);
        $display("Forward B = %b",forward_b);

        if ((forward_a == 2'b00) &&
            (forward_b == 2'b00))
            $display("PASS");
        else
            $display("FAIL");


        // =====================================================
        // COMPLETE
        // =====================================================

        $display("");
        $display("========================================");
        $display("FORWARDING UNIT TEST COMPLETE");
        $display("========================================");

        #10;

        $finish;

    end


    initial begin

        $dumpfile("riscv_forwarding.vcd");

        $dumpvars(0,tb_riscv_forwarding);

    end

endmodule

riscv_ai_accelerator.sim/sim_1/behav/xsim/riscv_forwarding.vcd
$date
   Thu Aug 13 21:20:46 2026
$end

$version
  2026.1
  $dumpfile ("riscv_forwarding.vcd") 
$end

$timescale
  1ps
$end

$scope module tb_riscv_forwarding $end
$var reg 5 ! idex_rs1 [4:0] $end
$var reg 5 " idex_rs2 [4:0] $end
$var reg 5 # exmem_rd [4:0] $end
$var reg 1 $ exmem_regwrite $end
$var reg 5 % memwb_rd [4:0] $end
$var reg 1 & memwb_regwrite $end
$var wire 2 ' forward_a [1:0] $end
$var wire 2 ( forward_b [1:0] $end
$scope module DUT $end
$var wire 5 ) idex_rs1 [4:0] $end
$var wire 5 * idex_rs2 [4:0] $end
$var wire 5 + exmem_rd [4:0] $end
$var wire 1 , exmem_regwrite $end
$var wire 5 - memwb_rd [4:0] $end
$var wire 1 . memwb_regwrite $end
$var reg 2 / forward_a [1:0] $end
$var reg 2 0 forward_b [1:0] $end
$upscope $end
$upscope $end
$enddefinitions $end

#0
$dumpvars
b1 !
b10 "
b11 #
1$
b100 %
1&
b0 '
b0 (
b1 )
b10 *
b11 +
1,
b100 -
1.
b0 /
b0 0
$end

#10000
b101 !
b101 #
b10 '
b101 )
b101 +
b10 /

#20000
b1 !
b110 "
b110 #
b0 '
b10 (
b1 )
b110 *
b110 +
b0 /
b10 0

#30000
b111 !
b10 "
b100 #
b111 %
b1 '
b0 (
b111 )
b10 *
b100 +
b111 -
b1 /
b0 0

#40000
b1 !
b1000 "
b1000 %
b0 '
b1 (
b1 )
b1000 *
b1000 -
b0 /
b1 0

#50000
b1010 !
b1011 "
b1010 #
b1011 %
b10 '
b1010 )
b1011 *
b1010 +
b1011 -
b10 /
b1 0

#60000
b1100 !
b10 "
b1100 #
b1100 %
b0 (
b1100 )
b10 *
b1100 +
b1100 -
b10 /
b0 0

#70000
b0 !
b0 "
b0 #
b0 %
b0 '
b0 )
b0 *
b0 +
b0 -
b0 /
