riscv_ai_accelerator.srcs/sources_1/new/riscv_alu.v
`timescale 1ns/1ps

module riscv_alu (
    input      [31:0] operand_a,
    input      [31:0] operand_b,

    input      [3:0]  alu_control,

    output reg [31:0] result,

    output            zero,
    output            less_than
);

    // =========================================================
    // ALU operation codes
    // =========================================================

    parameter ALU_ADD = 4'b0000;
    parameter ALU_SUB = 4'b0001;
    parameter ALU_AND = 4'b0010;
    parameter ALU_OR  = 4'b0011;
    parameter ALU_XOR = 4'b0100;
    parameter ALU_SLT = 4'b0101;
    parameter ALU_SLL = 4'b0110;
    parameter ALU_SRL = 4'b0111;
    parameter ALU_SRA = 4'b1000;


    // =========================================================
    // ALU
    // =========================================================

    always @(*) begin

        case (alu_control)

            // ADD
            ALU_ADD:
                result = operand_a + operand_b;


            // SUB
            ALU_SUB:
                result = operand_a - operand_b;


            // AND
            ALU_AND:
                result = operand_a & operand_b;


            // OR
            ALU_OR:
                result = operand_a | operand_b;


            // XOR
            ALU_XOR:
                result = operand_a ^ operand_b;


            // Signed Set Less Than
            ALU_SLT:
                result = ($signed(operand_a) <
                          $signed(operand_b)) ?
                          32'd1 : 32'd0;


            // Shift Left Logical
            ALU_SLL:
                result = operand_a << operand_b[4:0];


            // Shift Right Logical
            ALU_SRL:
                result = operand_a >> operand_b[4:0];


            // Shift Right Arithmetic
            ALU_SRA:
                result = $signed(operand_a) >>> operand_b[4:0];


            default:
                result = 32'd0;

        endcase

    end


    // =========================================================
    // Zero flag
    // =========================================================

    assign zero = (result == 32'd0);


    // =========================================================
    // Signed less-than flag
    // =========================================================

    assign less_than =
        ($signed(operand_a) < $signed(operand_b));

endmodule

riscv_ai_accelerator.srcs/sim_1/new/tb_riscv_alu.v
`timescale 1ns/1ps

module tb_riscv_alu;

    reg [31:0] operand_a;
    reg [31:0] operand_b;

    reg [3:0] alu_control;

    wire [31:0] result;

    wire zero;
    wire less_than;


    // =========================================================
    // ALU
    // =========================================================

    riscv_alu DUT (

        .operand_a(operand_a),
        .operand_b(operand_b),

        .alu_control(alu_control),

        .result(result),

        .zero(zero),
        .less_than(less_than)

    );

    localparam ALU_ADD = 4'b0000;
    localparam ALU_SUB = 4'b0001;
    localparam ALU_AND = 4'b0010;
    localparam ALU_OR  = 4'b0011;
    localparam ALU_XOR = 4'b0100;
    localparam ALU_SLT = 4'b0101;
    localparam ALU_SLL = 4'b0110;
    localparam ALU_SRL = 4'b0111;
    localparam ALU_SRA = 4'b1000;

    initial begin

        $display("========================================");
        $display("RISC-V ALU TEST");
        $display("========================================");


        // -----------------------------------------------------
        // ADD
        // -----------------------------------------------------

        operand_a   = 32'd10;
        operand_b   = 32'd20;
        alu_control = ALU_ADD;

        #10;

        $display("ADD: %d + %d = %d",
                 operand_a,
                 operand_b,
                 result);

        if (result == 32'd30)
            $display("PASS");
        else
            $display("FAIL");

        operand_a   = 32'd50;
        operand_b   = 32'd20;
        alu_control = ALU_SUB;

        #10;

        $display("SUB: %d - %d = %d",
                 operand_a,
                 operand_b,
                 result);

        if (result == 32'd30)
            $display("PASS");
        else
            $display("FAIL");


        // -----------------------------------------------------
        // AND
        // -----------------------------------------------------

        operand_a   = 32'hF0F0F0F0;
        operand_b   = 32'h0FF00FF0;
        alu_control = ALU_AND;

        #10;

        $display("AND: %h", result);

        if (result == 32'h00F000F0)
            $display("PASS");
        else
            $display("FAIL");

        operand_a   = 32'hF0000000;
        operand_b   = 32'h0000000F;
        alu_control = ALU_OR;

        #10;

        $display("OR: %h", result);

        if (result == 32'hF000000F)
            $display("PASS");
        else
            $display("FAIL");


        // -----------------------------------------------------
        // XOR
        // -----------------------------------------------------

        operand_a   = 32'hAAAAAAAA;
        operand_b   = 32'h55555555;
        alu_control = ALU_XOR;

        #10;

        $display("XOR: %h", result);

        if (result == 32'hFFFFFFFF)
            $display("PASS");
        else
            $display("FAIL");


        // -----------------------------------------------------
        // SLT
        // -----------------------------------------------------

        operand_a   = -32'sd10;
        operand_b   = 32'sd5;
        alu_control = ALU_SLT;

        #10;

        $display("SLT: -10 < 5 = %d", result);

        if (result == 32'd1)
            $display("PASS");
        else
            $display("FAIL");

        operand_a   = 32'd1;
        operand_b   = 32'd4;
        alu_control = ALU_SLL;

        #10;

        $display("SLL: 1 << 4 = %d", result);

        if (result == 32'd16)
            $display("PASS");
        else
            $display("FAIL");

        operand_a   = 32'd128;
        operand_b   = 32'd3;
        alu_control = ALU_SRL;

        #10;

        $display("SRL: 128 >> 3 = %d", result);

        if (result == 32'd16)
            $display("PASS");
        else
            $display("FAIL");


        // -----------------------------------------------------
        // SRA
        // -----------------------------------------------------

        operand_a   = 32'hFFFFFFF0;
        operand_b   = 32'd2;
        alu_control = ALU_SRA;

        #10;

        $display("SRA: FFFFFFF0 >>> 2 = %h", result);

        if (result == 32'hFFFFFFFC)
            $display("PASS");
        else
            $display("FAIL");


        operand_a   = 32'd25;
        operand_b   = 32'd25;
        alu_control = ALU_SUB;

        #10;

        $display("ZERO FLAG = %d", zero);

        if (zero == 1'b1)
            $display("PASS");
        else
            $display("FAIL");

        operand_a   = -32'sd5;
        operand_b   = 32'sd3;
        alu_control = ALU_SUB;

        #10;

        $display("LESS THAN FLAG = %d", less_than);

        if (less_than == 1'b1)
            $display("PASS");
        else
            $display("FAIL");

        $display("");
        $display("========================================");
        $display("ALU TEST COMPLETE");
        $display("========================================");

        #10;

        $finish;

    end

    initial begin

        $dumpfile("riscv_alu.vcd");

        $dumpvars(0, tb_riscv_alu);

    end

endmodule

riscv_ai_accelerator.sim/sim_1/behav/xsim/riscv_alu.vcd
$date
   Thu Aug 13 20:46:57 2026
$end

$version
  2026.1
  $dumpfile ("riscv_alu.vcd") 
$end

$timescale
  1ps
$end

$scope module tb_riscv_alu $end
$var reg 32 ! operand_a [31:0] $end
$var reg 32 " operand_b [31:0] $end
$var reg 4 # alu_control [3:0] $end
$var wire 32 $ result [31:0] $end
$var wire 1 % zero $end
$var wire 1 & less_than $end
$scope module DUT $end
$var wire 32 ' operand_a [31:0] $end
$var wire 32 ( operand_b [31:0] $end
$var wire 4 ) alu_control [3:0] $end
$var reg 32 * result [31:0] $end
$var wire 1 % zero $end
$var wire 1 & less_than $end
$upscope $end
$upscope $end
$enddefinitions $end

#0
$dumpvars
b1010 !
b10100 "
b0 #
b11110 $
0%
1&
b1010 '
b10100 (
b0 )
b11110 *
$end

#10000
b110010 !
b1 #
0&
b110010 '
b1 )

#20000
b11110000111100001111000011110000 !
b1111111100000000111111110000 "
b10 #
b111100000000000011110000 $
1&
b11110000111100001111000011110000 '
b1111111100000000111111110000 (
b10 )
b111100000000000011110000 *

#30000
b11110000000000000000000000000000 !
b1111 "
b11 #
b11110000000000000000000000001111 $
b11110000000000000000000000000000 '
b1111 (
b11 )
b11110000000000000000000000001111 *

#40000
b10101010101010101010101010101010 !
b1010101010101010101010101010101 "
b100 #
b11111111111111111111111111111111 $
b10101010101010101010101010101010 '
b1010101010101010101010101010101 (
b100 )
b11111111111111111111111111111111 *

#50000
b11111111111111111111111111110110 !
b101 "
b101 #
b1 $
b11111111111111111111111111110110 '
b101 (
b101 )
b1 *

#60000
b1 !
b100 "
b110 #
b10000 $
b1 '
b100 (
b110 )
b10000 *

#70000
b10000000 !
b11 "
b111 #
0&
b10000000 '
b11 (
b111 )

#80000
b11111111111111111111111111110000 !
b10 "
b1000 #
b11111111111111111111111111111100 $
1&
b11111111111111111111111111110000 '
b10 (
b1000 )
b11111111111111111111111111111100 *

#90000
b11001 !
b11001 "
b1 #
b0 $
1%
0&
b11001 '
b11001 (
b1 )
b0 *

#100000
b11111111111111111111111111111011 !
b11 "
b11111111111111111111111111111000 $
0%
1&
b11111111111111111111111111111011 '
b11 (
b11111111111111111111111111111000 *
