riscv_ai_accelerator.srcs/sources_1/new/riscv_regfile.v
`timescale 1ns/1ps

module riscv_regfile (
    input             clk,
    input             rst,

    input      [4:0]  rs1_addr,
    input      [4:0]  rs2_addr,

    output     [31:0] rs1_data,
    output     [31:0] rs2_data,

    input             rd_we,
    input      [4:0]  rd_addr,
    input      [31:0] rd_data
);

    reg [31:0] regs [0:31];

    integer i;


    // =========================================================
    // Read port 1 with write-through bypass
    // =========================================================

    assign rs1_data =
        (rs1_addr == 5'd0) ?
            32'd0 :

        (rd_we && (rd_addr != 5'd0) &&
         (rd_addr == rs1_addr)) ?
            rd_data :

            regs[rs1_addr];


    // =========================================================
    // Read port 2 with write-through bypass
    // =========================================================

    assign rs2_data =
        (rs2_addr == 5'd0) ?
            32'd0 :

        (rd_we && (rd_addr != 5'd0) &&
         (rd_addr == rs2_addr)) ?
            rd_data :

            regs[rs2_addr];


    // =========================================================
    // Register write
    // =========================================================

    always @(posedge clk or posedge rst) begin

        if (rst) begin

            for (i = 0; i < 32; i = i + 1)
                regs[i] <= 32'd0;

        end

        else begin

            if (rd_we && (rd_addr != 5'd0))
                regs[rd_addr] <= rd_data;

            regs[0] <= 32'd0;

        end

    end

endmodule

riscv_ai_accelerator.srcs/sim_1/new/tb_riscv_regfile.v
`timescale 1ns/1ps

module tb_riscv_regfile;

    reg clk;
    reg rst;

    reg [4:0] rs1_addr;
    reg [4:0] rs2_addr;

    wire [31:0] rs1_data;
    wire [31:0] rs2_data;

    reg rd_we;
    reg [4:0] rd_addr;
    reg [31:0] rd_data;


    // =========================================================
    // Instantiate Register File
    // =========================================================

    riscv_regfile DUT (

        .clk(clk),
        .rst(rst),

        .rs1_addr(rs1_addr),
        .rs2_addr(rs2_addr),

        .rs1_data(rs1_data),
        .rs2_data(rs2_data),

        .rd_we(rd_we),
        .rd_addr(rd_addr),
        .rd_data(rd_data)

    );


    // =========================================================
    // Clock generation
    // 10 ns period = 100 MHz
    // =========================================================

    initial begin
        clk = 1'b0;

        forever #5 clk = ~clk;
    end


    // =========================================================
    // Test sequence
    // =========================================================

    initial begin

        // Initial values
        rst      = 1'b1;

        rs1_addr = 5'd0;
        rs2_addr = 5'd0;

        rd_we    = 1'b0;
        rd_addr  = 5'd0;
        rd_data  = 32'd0;


        // -----------------------------------------------------
        // RESET
        // -----------------------------------------------------

        #20;

        rst = 1'b0;

        $display("----------------------------------------");
        $display("RESET COMPLETE");
        $display("----------------------------------------");


        // =====================================================
        // TEST 1
        // Write 100 into x5
        // =====================================================

        @(negedge clk);

        rd_we   = 1'b1;
        rd_addr = 5'd5;
        rd_data = 32'd100;

        @(negedge clk);

        rd_we = 1'b0;


        // Read x5
        rs1_addr = 5'd5;

        #2;

        $display("TEST 1:");
        $display("x5 = %d", rs1_data);

        if (rs1_data == 32'd100)
            $display("PASS: x5 contains 100");
        else
            $display("FAIL: x5 does not contain 100");


        // =====================================================
        // TEST 2
        // Write 200 into x10
        // =====================================================

        @(negedge clk);

        rd_we   = 1'b1;
        rd_addr = 5'd10;
        rd_data = 32'd200;

        @(negedge clk);

        rd_we = 1'b0;


        // Read x10
        rs1_addr = 5'd10;

        #2;

        $display("");
        $display("TEST 2:");
        $display("x10 = %d", rs1_data);

        if (rs1_data == 32'd200)
            $display("PASS: x10 contains 200");
        else
            $display("FAIL: x10 does not contain 200");


        // =====================================================
        // TEST 3
        // Test TWO read ports simultaneously
        // =====================================================

        rs1_addr = 5'd5;
        rs2_addr = 5'd10;

        #2;

        $display("");
        $display("TEST 3:");
        $display("rs1 = x5  = %d", rs1_data);
        $display("rs2 = x10 = %d", rs2_data);

        if ((rs1_data == 32'd100) &&
            (rs2_data == 32'd200))
            $display("PASS: dual read ports working");
        else
            $display("FAIL: dual read ports");


        // =====================================================
        // TEST 4
        // Verify x0 is ALWAYS zero
        // =====================================================

        rs1_addr = 5'd0;

        #2;

        $display("");
        $display("TEST 4:");
        $display("x0 = %d", rs1_data);

        if (rs1_data == 32'd0)
            $display("PASS: x0 is zero");
        else
            $display("FAIL: x0 is not zero");


        // =====================================================
        // TEST 5
        // Attempt to write x0
        // =====================================================

        @(negedge clk);

        rd_we   = 1'b1;
        rd_addr = 5'd0;
        rd_data = 32'hFFFFFFFF;

        @(negedge clk);

        rd_we = 1'b0;

        rs1_addr = 5'd0;

        #2;

        $display("");
        $display("TEST 5:");
        $display("Attempted x0 = FFFFFFFF");
        $display("Actual x0    = %h", rs1_data);

        if (rs1_data == 32'd0)
            $display("PASS: x0 cannot be modified");
        else
            $display("FAIL: x0 was modified");


        // =====================================================
        // END
        // =====================================================

        $display("");
        $display("========================================");
        $display("REGISTER FILE TEST COMPLETE");
        $display("========================================");

        #20;

        $finish;

    end


    // =========================================================
    // Waveform dump
    // =========================================================

    initial begin

        $dumpfile("riscv_regfile.vcd");

        $dumpvars(0, tb_riscv_regfile);

    end

endmodule

riscv_ai_accelerator.sim/sim_1/behav/xsim/riscv_regfile.vcd
$date
   Thu Aug 13 21:40:00 2026
$end

$version
  2026.1
  $dumpfile ("riscv_regfile.vcd") 
$end

$timescale
  1ps
$end

$scope module tb_riscv_regfile $end
$var reg 1 ! clk $end
$var reg 1 " rst $end
$var reg 5 # rs1_addr [4:0] $end
$var reg 5 $ rs2_addr [4:0] $end
$var wire 32 % rs1_data [31:0] $end
$var wire 32 & rs2_data [31:0] $end
$var reg 1 ' rd_we $end
$var reg 5 ( rd_addr [4:0] $end
$var reg 32 ) rd_data [31:0] $end
$scope module DUT $end
$var wire 1 * clk $end
$var wire 1 + rst $end
$var wire 5 , rs1_addr [4:0] $end
$var wire 5 - rs2_addr [4:0] $end
$var wire 32 % rs1_data [31:0] $end
$var wire 32 & rs2_data [31:0] $end
$var wire 1 . rd_we $end
$var wire 5 / rd_addr [4:0] $end
$var wire 32 0 rd_data [31:0] $end
$var integer 32 1 i [31:0] $end
$upscope $end
$upscope $end
$enddefinitions $end

#0
$dumpvars
0!
1"
b0 #
b0 $
b0 %
b0 &
0'
b0 (
b0 )
0*
1+
b0 ,
b0 -
0.
b0 /
b0 0
bx 1
$end

#5000
1!
1*

#10000
0!
0*

#15000
1!
1*

#20000
0!
0"
1'
b101 (
b1100100 )
0*
0+
1.
b101 /
b1100100 0

#25000
1!
1*

#30000
0!
b101 #
b1100100 %
0'
0*
b101 ,
0.

#35000
1!
1*

#40000
0!
1'
b1010 (
b11001000 )
0*
1.
b1010 /
b11001000 0

#45000
1!
1*

#50000
0!
b1010 #
b11001000 %
0'
0*
b1010 ,
0.

#52000
b101 #
b1010 $
b1100100 %
b11001000 &
b101 ,
b1010 -

#54000
b0 #
b0 %
b0 ,

#55000
1!
1*

#60000
0!
1'
b0 (
b11111111111111111111111111111111 )
0*
1.
b0 /
b11111111111111111111111111111111 0

#65000
1!
1*

#70000
0!
0'
0*
0.

